Workbook

Sheet Калькулятор
A4: Введите свои значения | O4: Комиссия за продажу | S4: Логистика | V4: Хранение
A6: № | B6: Category ID | C6: Категория 1 | D6: Категория 2 | E6: Категория 2 | F6: Категория 5 | G6: Категория 6 | H6: Цена за единицу товара (сум) | I6: Длина (мм) | J6: Ширина (мм) | K6: Высота (мм) | L6: Оборачиваемость (дни) | M6: Схема работы (FBO / FBS / DBS) | O6: Процент (%) комиссии (c учетом скидок) | P6: Размер (%) скидки (для инфо) (при наличии) | Q6: Комиссионный сбор (сум) | S6: Объем (л) | T6: Лог. Сбор (1 товар) | V6: Объем (л) | W6: Группа по оборачиваемости | X6: Кол-во дней бесплатного хранения нового стока (для инфо) (дней) | Y6: Тип тарифа (стандартный /специальный) | Z6: Тариф за 1 литр в день (сум) | AA6: Сбор за хранение за 1 товар в день (сум)
A8: 1 | B8: 17726 | C8: =VLOOKUP(B8, 'Комиссия на продажу'!$A$5:$H$6420, 3, 0) -> Строительство и ремонт | D8: =VLOOKUP(B8, 'Комиссия на продажу'!$A$5:$H$6420, 4, 0) -> Лакокрасочные материалы | E8: =VLOOKUP(B8, 'Комиссия на продажу'!$A$5:$H$6420, 5, 0) -> Краски | F8: =VLOOKUP(B8, 'Комиссия на продажу'!$A$5:$H$6420, 6, 0) -> Краски для наружных работ | G8: =VLOOKUP(B8, 'Комиссия на продажу'!$A$5:$H$6420, 7, 0) -> Масляные | H8: 80000 | I8: 700 | J8: 300 | K8: 80 | L8: 100 | M8: FBS | O8: {=INDEX('Комиссия на продажу'!$O$5:$Q$6410, MATCH($B8, 'Комиссия на продажу'!$A$5:$A$6410, 0), MATCH($M8, 'Комиссия на продажу'!$O$4:$Q$4, 0))} -> -% | P8: {=INDEX('Комиссия на продажу'!$L$5:$N$6410, MATCH($B8, 'Комиссия на продажу'!$A$5:$A$6410, 0), MATCH($M8, 'Комиссия на продажу'!$O$4:$Q$4, 0))} -> -% | Q8: =IFERROR(H8 * O8, "Данной категории нет в выбранной схеме работы") -> Данной категории нет в выбранной схеме работы | S8: =ROUNDUP(I8 * J8 * K8 / 10^6, 0) -> 17 | T8: =IF(M8 = "DBS", 0, MIN('Тариф на логистику (логсбор)'!$A$3 + ($S8 - 1) * 'Тариф на логистику (логсбор)'!$A$4, 'Тариф на логистику (логсбор)'!$A$6)) -> 9250 | V8: =ROUNDUP(I8 * J8 * K8 / 10^6, 0) -> 17 | W8: =IF(AND(M8 = "FBO", O8 <> "-%"), LOOKUP(L8, 'Тариф на хранение'!$E$5:$E$8, 'Тариф на хранение'!$A$5:$A$8), "-") -> - | X8: =IF(AND(M8 = "FBO", O8 <> "-%"), IFERROR(VLOOKUP(D8, 'Приложение 2'!$B:$C, 2, 0), 30), "-") -> - | Y8: =IF(AND(M8 = "FBO", O8 <> "-%"), IFERROR(VLOOKUP(D8, 'Приложение 1'!$B:$C, 2, 0), "Стандартный"), "-") -> - | Z8: =IF(AND(M8 = "FBO", O8 <> "-%"), IF(Y8 = "Стандартный", SUMIFS('Тариф на хранение'!$D$5:$D$8, 'Тариф на хранение'!$A$5:$A$8, W8) , SUMIFS('Тариф на хранение'!$D$14:$D$17, 'Тариф на хранение'!$A$14:$A$17, W8)), 0) -> 0 | AA8: =IF(Y8 = "Стандартный" , MIN('Тариф на хранение'!$D$10, Z8 * V8) , MIN('Тариф на хранение'!$D$19, Z8 * V8)) -> 0
A9: 2 | B9: 2828 | C9: =VLOOKUP(B9, 'Комиссия на продажу'!$A$5:$H$6420, 3, 0) -> Одежда | D9: =VLOOKUP(B9, 'Комиссия на продажу'!$A$5:$H$6420, 4, 0) -> Женская одежда | E9: =VLOOKUP(B9, 'Комиссия на продажу'!$A$5:$H$6420, 5, 0) -> Спортивная одежда | F9: =VLOOKUP(B9, 'Комиссия на продажу'!$A$5:$H$6420, 6, 0) -> Спортивные носки и гольфы | G9: =VLOOKUP(B9, 'Комиссия на продажу'!$A$5:$H$6420, 7, 0) | H9: 250000 | I9: 200 | J9: 100 | K9: 50 | L9: 92 | M9: FBO | O9: {=INDEX('Комиссия на продажу'!$O$5:$Q$6410, MATCH($B9, 'Комиссия на продажу'!$A$5:$A$6410, 0), MATCH($M9, 'Комиссия на продажу'!$O$4:$Q$4, 0))} -> 0.25 | P9: {=INDEX('Комиссия на продажу'!$L$5:$N$6410, MATCH($B9, 'Комиссия на продажу'!$A$5:$A$6410, 0), MATCH($M9, 'Комиссия на продажу'!$O$4:$Q$4, 0))} -> 0 | Q9: =H9 * O9 -> 62500 | S9: =ROUNDUP(I9 * J9 * K9 / 10^6, 0) -> 1 | T9: =IF(M9 = "DBS", 0, MIN('Тариф на логистику (логсбор)'!$A$3 + ($S9 - 1) * 'Тариф на логистику (логсбор)'!$A$4, 'Тариф на логистику (логсбор)'!$A$6)) -> 5250 | V9: =ROUNDUP(I9 * J9 * K9 / 10^6, 0) -> 1 | W9: =IF(AND(M9 = "FBO", O9 <> "-%"), LOOKUP(L9, 'Тариф на хранение'!$E$5:$E$8, 'Тариф на хранение'!$A$5:$A$8), "-") -> 61–180 дней | X9: =IF(AND(M9 = "FBO", O9 <> "-%"), IFERROR(VLOOKUP(D9, 'Приложение 2'!$B:$C, 2, 0), 30), "-") -> 60 | Y9: =IF(AND(M9 = "FBO", O9 <> "-%"), IFERROR(VLOOKUP(D9, 'Приложение 1'!$B:$C, 2, 0), "Стандартный"), "-") -> Специальный | Z9: =IF(AND(M9 = "FBO", O9 <> "-%"), IF(Y9 = "Стандартный", SUMIFS('Тариф на хранение'!$D$5:$D$8, 'Тариф на хранение'!$A$5:$A$8, W9) , SUMIFS('Тариф на хранение'!$D$14:$D$17, 'Тариф на хранение'!$A$14:$A$17, W9)), 0) -> 12 | AA9: =IF(Y9 = "Стандартный" , MIN('Тариф на хранение'!$D$10, Z9 * V9) , MIN('Тариф на хранение'!$D$19, Z9 * V9)) -> 12
A10: 3 | B10: 12429 | C10: =VLOOKUP(B10, 'Комиссия на продажу'!$A$5:$H$6420, 3, 0) -> Бытовая химия | D10: =VLOOKUP(B10, 'Комиссия на продажу'!$A$5:$H$6420, 4, 0) -> Средства от насекомых и грызунов | E10: =VLOOKUP(B10, 'Комиссия на продажу'!$A$5:$H$6420, 5, 0) -> Ратициды | F10: =VLOOKUP(B10, 'Комиссия на продажу'!$A$5:$H$6420, 6, 0) | G10: =VLOOKUP(B10, 'Комиссия на продажу'!$A$5:$H$6420, 7, 0) | H10: 30000 | I10: 100 | J10: 400 | K10: 150 | L10: 185 | M10: FBS | O10: {=INDEX('Комиссия на продажу'!$O$5:$Q$6410, MATCH($B10, 'Комиссия на продажу'!$A$5:$A$6410, 0), MATCH($M10, 'Комиссия на продажу'!$O$4:$Q$4, 0))} -> 0.17 | P10: {=INDEX('Комиссия на продажу'!$L$5:$N$6410, MATCH($B10, 'Комиссия на продажу'!$A$5:$A$6410, 0), MATCH($M10, 'Комиссия на продажу'!$O$4:$Q$4, 0))} -> 0.03 | Q10: =H10 * O10 -> 5100 | S10: =ROUNDUP(I10 * J10 * K10 / 10^6, 0) -> 6 | T10: =IF(M10 = "DBS", 0, MIN('Тариф на логистику (логсбор)'!$A$3 + ($S10 - 1) * 'Тариф на логистику (логсбор)'!$A$4, 'Тариф на логистику (логсбор)'!$A$6)) -> 6500 | V10: =ROUNDUP(I10 * J10 * K10 / 10^6, 0) -> 6 | W10: =IF(AND(M10 = "FBO", O10 <> "-%"), LOOKUP(L10, 'Тариф на хранение'!$E$5:$E$8, 'Тариф на хранение'!$A$5:$A$8), "-") -> - | X10: =IF(AND(M10 = "FBO", O10 <> "-%"), IFERROR(VLOOKUP(D10, 'Приложение 2'!$B:$C, 2, 0), 30), "-") -> - | Y10: =IF(AND(M10 = "FBO", O10 <> "-%"), IFERROR(VLOOKUP(D10, 'Приложение 1'!$B:$C, 2, 0), "Стандартный"), "-") -> - | Z10: =IF(AND(M10 = "FBO", O10 <> "-%"), IF(Y10 = "Стандартный", SUMIFS('Тариф на хранение'!$D$5:$D$8, 'Тариф на хранение'!$A$5:$A$8, W10) , SUMIFS('Тариф на хранение'!$D$14:$D$17, 'Тариф на хранение'!$A$14:$A$17, W10)), 0) -> 0 | AA10: =IF(Y10 = "Стандартный" , MIN('Тариф на хранение'!$D$10, Z10 * V10) , MIN('Тариф на хранение'!$D$19, Z10 * V10)) -> 0
A11: 4 | B11: 10912 | C11: =VLOOKUP(B11, 'Комиссия на продажу'!$A$5:$H$6420, 3, 0) -> Обувь | D11: =VLOOKUP(B11, 'Комиссия на продажу'!$A$5:$H$6420, 4, 0) -> Обувь для мальчиков | E11: =VLOOKUP(B11, 'Комиссия на продажу'!$A$5:$H$6420, 5, 0) -> Резиновая обувь | F11: =VLOOKUP(B11, 'Комиссия на продажу'!$A$5:$H$6420, 6, 0) -> Сандалии | G11: =VLOOKUP(B11, 'Комиссия на продажу'!$A$5:$H$6420, 7, 0) | H11: 50000 | I11: 100 | J11: 400 | K11: 150 | L11: 365 | M11: FBO | O11: {=INDEX('Комиссия на продажу'!$O$5:$Q$6410, MATCH($B11, 'Комиссия на продажу'!$A$5:$A$6410, 0), MATCH($M11, 'Комиссия на продажу'!$O$4:$Q$4, 0))} -> 0.2 | P11: {=INDEX('Комиссия на продажу'!$L$5:$N$6410, MATCH($B11, 'Комиссия на продажу'!$A$5:$A$6410, 0), MATCH($M11, 'Комиссия на продажу'!$O$4:$Q$4, 0))} -> 0 | Q11: =H11 * O11 -> 10000 | S11: =ROUNDUP(I11 * J11 * K11 / 10^6, 0) -> 6 | T11: =IF(M11 = "DBS", 0, MIN('Тариф на логистику (логсбор)'!$A$3 + ($S11 - 1) * 'Тариф на логистику (логсбор)'!$A$4, 'Тариф на логистику (логсбор)'!$A$6)) -> 6500 | V11: =ROUNDUP(I11 * J11 * K11 / 10^6, 0) -> 6 | W11: =IF(AND(M11 = "FBO", O11 <> "-%"), LOOKUP(L11, 'Тариф на хранение'!$E$5:$E$8, 'Тариф на хранение'!$A$5:$A$8), "-") -> 361 и более дней** | X11: =IF(AND(M11 = "FBO", O11 <> "-%"), IFERROR(VLOOKUP(D11, 'Приложение 2'!$B:$C, 2, 0), 30), "-") -> 60 | Y11: =IF(AND(M11 = "FBO", O11 <> "-%"), IFERROR(VLOOKUP(D11, 'Приложение 1'!$B:$C, 2, 0), "Стандартный"), "-") -> Специальный | Z11: =IF(AND(M11 = "FBO", O11 <> "-%"), IF(Y11 = "Стандартный", SUMIFS('Тариф на хранение'!$D$5:$D$8, 'Тариф на хранение'!$A$5:$A$8, W11) , SUMIFS('Тариф на хранение'!$D$14:$D$17, 'Тариф на хранение'!$A$14:$A$17, W11)), 0) -> 18 | AA11: =IF(Y11 = "Стандартный" , MIN('Тариф на хранение'!$D$10, Z11 * V11) , MIN('Тариф на хранение'!$D$19, Z11 * V11)) -> 108

Sheet Kalkulyator
A4: Qiymatlarni kiriting | O4: Sotuv uchun komissiya | S4: Logistika | V4: Saqlash
A6: № | B6: Category ID | C6: Toifa 1 | D6: Toifa 2 | E6: Toifa 3 | F6: Toifa 5 | G6: Toifa 6 | H6: Tovar birligi narxi (so‘m) | I6: Uzunligi (mm) | J6: Kengligi (mm) | K6: Balandligi (mm) | L6: Aylanuvchanlik (kun) | M6: Ish sxemasi (FBO / FBS / DBS) | O6: Komissiya foizi (%) (chegirmalarni hisobga olgan holda) | P6: Chegirma miqdori (%) (ma’lumot uchun) (mavjud bo‘lsa) | Q6: Komissiya yig‘imi (so‘m) | S6: Hajmi (l) | T6: Log. Yig‘im (1 ta tovar) | V6: Hajmi (l) | W6: Aylanma bo‘yicha guruh | X6: Yangi stok uchun bepul saqlash kunlari soni (ma’lumot uchun) (kunlarda) | Y6: Tarif turi (standart /maxsus) | Z6: Kuniga 1 litr uchun tarif (so‘m) | AA6: Kuniga 1 ta tovar uchun saqlash haqi (so‘m)
A8: 1 | B8: 12622 | C8: =VLOOKUP(B8, 'Savdo komissiyasi'!$A$5:$H$6420, 3, 0) -> Elektronika | D8: =VLOOKUP(B8, 'Savdo komissiyasi'!$A$5:$H$6420, 4, 0) -> Elektronikalar uchun aksessuarlar | E8: =VLOOKUP(B8, 'Savdo komissiyasi'!$A$5:$H$6420, 5, 0) -> Kabellar uchun organayzerlar | F8: =VLOOKUP(B8, 'Savdo komissiyasi'!$A$5:$H$6420, 6, 0) | G8: =VLOOKUP(B8, 'Savdo komissiyasi'!$A$5:$H$6420, 7, 0) | H8: 25000 | I8: 210 | J8: 220 | K8: 0 | L8: 365 | M8: FBO | O8: {=INDEX('Savdo komissiyasi'!$O$5:$Q$6410, MATCH($B8, 'Savdo komissiyasi'!$A$5:$A$6410, 0), MATCH($M8, 'Savdo komissiyasi'!$O$4:$Q$4, 0))} -> 0.3 | P8: {=INDEX('Savdo komissiyasi'!$L$5:$N$6410, MATCH($B8, 'Savdo komissiyasi'!$A$5:$A$6410, 0), MATCH($M8, 'Savdo komissiyasi'!$O$4:$Q$4, 0))} -> 0 | Q8: =IFERROR(H8 * O8, "Bu toifa tanlangan ish sxemasida mavjud emas") -> 7500 | S8: =ROUNDUP(I8 * J8 * K8 / 10^6, 0) -> 0 | T8: =IF(M8 = "DBS", 0, MIN('Logistika tarifi (log-yig‘im)'!$A$3 + ($S8 - 1) * 'Logistika tarifi (log-yig‘im)'!$A$4, 'Logistika tarifi (log-yig‘im)'!$A$6)) -> 5000 | V8: =ROUNDUP(I8 * J8 * K8 / 10^6, 0) -> 0 | W8: =IF(AND(M8 = "FBO", O8 <> "-%"), LOOKUP(L8, 'Saqlash uchun tarif'!$E$5:$E$8, 'Saqlash uchun tarif'!$A$5:$A$8), "-") -> 361 va undan ortiq kun* | X8: =IF(AND(M8 = "FBO", O8 <> "-%"), IFERROR(VLOOKUP(D8, '2-ilova'!$B:$C, 2, 0), 30), "-") -> 60 | Y8: =IF(AND(M8 = "FBO", O8 <> "-%"), IFERROR(VLOOKUP(D8, '1-ilova'!$B:$C, 2, 0), "Standart"), "-") -> Maxsus | Z8: =IF(AND(M8 = "FBO", O8 <> "-%"), IF(Y8 = "Стандартный", SUMIFS('Saqlash uchun tarif'!$D$5:$D$8, 'Saqlash uchun tarif'!$A$5:$A$8, W8) , SUMIFS('Saqlash uchun tarif'!$D$14:$D$17, 'Saqlash uchun tarif'!$A$14:$A$17, W8)), 0) -> 18 | AA8: =IF(Y8 = "Стандартный" , MIN('Saqlash uchun tarif'!$D$10, Z8 * V8) , MIN('Saqlash uchun tarif'!$D$19, Z8 * V8)) -> 0
A9: 2 | B9: 13871 | C9: =VLOOKUP(B9, 'Savdo komissiyasi'!$A$5:$H$6420, 3, 0) -> Elektronika | D9: =VLOOKUP(B9, 'Savdo komissiyasi'!$A$5:$H$6420, 4, 0) -> Ofis texnikasi | E9: =VLOOKUP(B9, 'Savdo komissiyasi'!$A$5:$H$6420, 5, 0) -> Ofis jihozlari uchun butlovchi qismlar | F9: =VLOOKUP(B9, 'Savdo komissiyasi'!$A$5:$H$6420, 6, 0) -> 3D printer uchun plastik | G9: =VLOOKUP(B9, 'Savdo komissiyasi'!$A$5:$H$6420, 7, 0) | H9: 269000 | I9: 210 | J9: 210 | K9: 70 | L9: 365 | M9: FBS | O9: {=INDEX('Savdo komissiyasi'!$O$5:$Q$6410, MATCH($B9, 'Savdo komissiyasi'!$A$5:$A$6410, 0), MATCH($M9, 'Savdo komissiyasi'!$O$4:$Q$4, 0))} -> 0.3 | P9: {=INDEX('Savdo komissiyasi'!$L$5:$N$6410, MATCH($B9, 'Savdo komissiyasi'!$A$5:$A$6410, 0), MATCH($M9, 'Savdo komissiyasi'!$O$4:$Q$4, 0))} -> 0 | Q9: =H9 * O9 -> 80700 | S9: =ROUNDUP(I9 * J9 * K9 / 10^6, 0) -> 4 | T9: =IF(M9 = "DBS", 0, MIN('Logistika tarifi (log-yig‘im)'!$A$3 + ($S9 - 1) * 'Logistika tarifi (log-yig‘im)'!$A$4, 'Logistika tarifi (log-yig‘im)'!$A$6)) -> 6000 | V9: =ROUNDUP(I9 * J9 * K9 / 10^6, 0) -> 4 | W9: =IF(AND(M9 = "FBO", O9 <> "-%"), LOOKUP(L9, 'Saqlash uchun tarif'!$E$5:$E$8, 'Saqlash uchun tarif'!$A$5:$A$8), "-") -> - | X9: =IF(AND(M9 = "FBO", O9 <> "-%"), IFERROR(VLOOKUP(D9, '2-ilova'!$B:$C, 2, 0), 30), "-") -> - | Y9: =IF(AND(M9 = "FBO", O9 <> "-%"), IFERROR(VLOOKUP(D9, '1-ilova'!$B:$C, 2, 0), "Standart"), "-") -> - | Z9: =IF(AND(M9 = "FBO", O9 <> "-%"), IF(Y9 = "Стандартный", SUMIFS('Saqlash uchun tarif'!$D$5:$D$8, 'Saqlash uchun tarif'!$A$5:$A$8, W9) , SUMIFS('Saqlash uchun tarif'!$D$14:$D$17, 'Saqlash uchun tarif'!$A$14:$A$17, W9)), 0) -> 0 | AA9: =IF(Y9 = "Стандартный" , MIN('Saqlash uchun tarif'!$D$10, Z9 * V9) , MIN('Saqlash uchun tarif'!$D$19, Z9 * V9)) -> 0
A10: 3 | B10: 12429 | C10: =VLOOKUP(B10, 'Savdo komissiyasi'!$A$5:$H$6420, 3, 0) -> Maishiy kimyoviy moddalar | D10: =VLOOKUP(B10, 'Savdo komissiyasi'!$A$5:$H$6420, 4, 0) -> Hasharotlar va kemiruvchilarga qarshi vositalar | E10: =VLOOKUP(B10, 'Savdo komissiyasi'!$A$5:$H$6420, 5, 0) -> Ratisidlar | F10: =VLOOKUP(B10, 'Savdo komissiyasi'!$A$5:$H$6420, 6, 0) | G10: =VLOOKUP(B10, 'Savdo komissiyasi'!$A$5:$H$6420, 7, 0) | H10: 30000 | I10: 100 | J10: 400 | K10: 150 | L10: 185 | M10: FBO | O10: {=INDEX('Savdo komissiyasi'!$O$5:$Q$6410, MATCH($B10, 'Savdo komissiyasi'!$A$5:$A$6410, 0), MATCH($M10, 'Savdo komissiyasi'!$O$4:$Q$4, 0))} -> 0.17 | P10: {=INDEX('Savdo komissiyasi'!$L$5:$N$6410, MATCH($B10, 'Savdo komissiyasi'!$A$5:$A$6410, 0), MATCH($M10, 'Savdo komissiyasi'!$O$4:$Q$4, 0))} -> 0.03 | Q10: =H10 * O10 -> 5100 | S10: =ROUNDUP(I10 * J10 * K10 / 10^6, 0) -> 6 | T10: =IF(M10 = "DBS", 0, MIN('Logistika tarifi (log-yig‘im)'!$A$3 + ($S10 - 1) * 'Logistika tarifi (log-yig‘im)'!$A$4, 'Logistika tarifi (log-yig‘im)'!$A$6)) -> 6500 | V10: =ROUNDUP(I10 * J10 * K10 / 10^6, 0) -> 6 | W10: =IF(AND(M10 = "FBO", O10 <> "-%"), LOOKUP(L10, 'Saqlash uchun tarif'!$E$5:$E$8, 'Saqlash uchun tarif'!$A$5:$A$8), "-") -> 181–360 kun | X10: =IF(AND(M10 = "FBO", O10 <> "-%"), IFERROR(VLOOKUP(D10, '2-ilova'!$B:$C, 2, 0), 30), "-") -> 30 | Y10: =IF(AND(M10 = "FBO", O10 <> "-%"), IFERROR(VLOOKUP(D10, '1-ilova'!$B:$C, 2, 0), "Standart"), "-") -> Standart | Z10: =IF(AND(M10 = "FBO", O10 <> "-%"), IF(Y10 = "Стандартный", SUMIFS('Saqlash uchun tarif'!$D$5:$D$8, 'Saqlash uchun tarif'!$A$5:$A$8, W10) , SUMIFS('Saqlash uchun tarif'!$D$14:$D$17, 'Saqlash uchun tarif'!$A$14:$A$17, W10)), 0) -> 14 | AA10: =IF(Y10 = "Стандартный" , MIN('Saqlash uchun tarif'!$D$10, Z10 * V10) , MIN('Saqlash uchun tarif'!$D$19, Z10 * V10)) -> 84
A11: 4 | B11: 2651 | C11: =VLOOKUP(B11, 'Savdo komissiyasi'!$A$5:$H$6420, 3, 0) -> Salomatlik | D11: =VLOOKUP(B11, 'Savdo komissiyasi'!$A$5:$H$6420, 4, 0) -> Optika | E11: =VLOOKUP(B11, 'Savdo komissiyasi'!$A$5:$H$6420, 5, 0) -> Salfetkalar, koʻzoynak uchun spreylar | F11: =VLOOKUP(B11, 'Savdo komissiyasi'!$A$5:$H$6420, 6, 0) | G11: =VLOOKUP(B11, 'Savdo komissiyasi'!$A$5:$H$6420, 7, 0) | H11: 50000 | I11: 100 | J11: 400 | K11: 150 | L11: 365 | M11: FBO | O11: {=INDEX('Savdo komissiyasi'!$O$5:$Q$6410, MATCH($B11, 'Savdo komissiyasi'!$A$5:$A$6410, 0), MATCH($M11, 'Savdo komissiyasi'!$O$4:$Q$4, 0))} -> 0.325 | P11: {=INDEX('Savdo komissiyasi'!$L$5:$N$6410, MATCH($B11, 'Savdo komissiyasi'!$A$5:$A$6410, 0), MATCH($M11, 'Savdo komissiyasi'!$O$4:$Q$4, 0))} -> 0.025 | Q11: =H11 * O11 -> 16250 | S11: =ROUNDUP(I11 * J11 * K11 / 10^6, 0) -> 6 | T11: =IF(M11 = "DBS", 0, MIN('Logistika tarifi (log-yig‘im)'!$A$3 + ($S11 - 1) * 'Logistika tarifi (log-yig‘im)'!$A$4, 'Logistika tarifi (log-yig‘im)'!$A$6)) -> 6500 | V11: =ROUNDUP(I11 * J11 * K11 / 10^6, 0) -> 6 | W11: =IF(AND(M11 = "FBO", O11 <> "-%"), LOOKUP(L11, 'Saqlash uchun tarif'!$E$5:$E$8, 'Saqlash uchun tarif'!$A$5:$A$8), "-") -> 361 va undan ortiq kun* | X11: =IF(AND(M11 = "FBO", O11 <> "-%"), IFERROR(VLOOKUP(D11, '2-ilova'!$B:$C, 2, 0), 30), "-") -> 60 | Y11: =IF(AND(M11 = "FBO", O11 <> "-%"), IFERROR(VLOOKUP(D11, '1-ilova'!$B:$C, 2, 0), "Standart"), "-") -> Standart | Z11: =IF(AND(M11 = "FBO", O11 <> "-%"), IF(Y11 = "Стандартный", SUMIFS('Saqlash uchun tarif'!$D$5:$D$8, 'Saqlash uchun tarif'!$A$5:$A$8, W11) , SUMIFS('Saqlash uchun tarif'!$D$14:$D$17, 'Saqlash uchun tarif'!$A$14:$A$17, W11)), 0) -> 18 | AA11: =IF(Y11 = "Стандартный" , MIN('Saqlash uchun tarif'!$D$10, Z11 * V11) , MIN('Saqlash uchun tarif'!$D$19, Z11 * V11)) -> 108

Sheet Комиссия на продажу
I2: Комиссия до скидки | L2: Размер скидки (скидка длится до 19.07.2026 включительно) | O2: Комиссия после скидки
A3: category ID | B3: cat_code | C3: category1_ru | D3: category2_ru | E3: category3_ru | F3: category4_ru | G3: category5_ru | H3: category6_ru | I3: comm FBO % | J3: comm FBS % | K3: comm DBS% | L3: Скидка FBO % | M3: Скидка FBS % | N3: Скидка DBS% | O3: comm FBO % | P3: comm FBS % | Q3: comm DBS%
I4: FBO | J4: FBS | K4: DBS | L4: FBO | M4: FBS | N4: DBS | O4: FBO | P4: FBS | Q4: DBS
A5: 11 | B5: =C5&D5&E5&F5&G5&H5 -> Бытовая техникаКрупная бытовая техникаДуховые шкафы | C5: Бытовая техника | D5: Крупная бытовая техника | E5: Духовые шкафы | I5: 0.1 | J5: 0.1 | K5: 0.1 | L5: 0 | M5: 0 | N5: 0 | O5: 0.1 | P5: 0.1 | Q5: 0.1
A6: 13 | B6: =C6&D6&E6&F6&G6&H6 -> Бытовая техникаКрупная бытовая техникаПлитыГазовые плиты | C6: Бытовая техника | D6: Крупная бытовая техника | E6: Плиты | F6: Газовые плиты | I6: 0.1 | J6: 0.1 | K6: 0.1 | L6: 0 | M6: 0 | N6: 0 | O6: 0.1 | P6: 0.1 | Q6: 0.1
A7: 14 | B7: =C7&D7&E7&F7&G7&H7 -> КнигиРелигиозные книгиХристианствоСвященные тексты | C7: Книги | D7: Религиозные книги | E7: Христианство | F7: Священные тексты | I7: 0.2 | J7: 0.2 | K7: 0.2 | L7: 0 | M7: 0 | N7: 0 | O7: 0.2 | P7: 0.2 | Q7: 0.2
A8: 16 | B8: =C8&D8&E8&F8&G8&H8 -> Бытовая техникаКрупная бытовая техникаСушильные машины | C8: Бытовая техника | D8: Крупная бытовая техника | E8: Сушильные машины | I8: 0.1 | J8: 0.1 | K8: 0.1 | L8: 0 | M8: 0 | N8: 0 | O8: 0.1 | P8: 0.1 | Q8: 0.1
A9: 17 | B9: =C9&D9&E9&F9&G9&H9 -> Бытовая техникаКрупная бытовая техникаПосудомоечные машины | C9: Бытовая техника | D9: Крупная бытовая техника | E9: Посудомоечные машины | I9: 0.1 | J9: 0.1 | K9: 0.1 | L9: 0 | M9: 0 | N9: 0 | O9: 0.1 | P9: 0.1 | Q9: 0.1
A10: 22 | B10: =C10&D10&E10&F10&G10&H10 -> Строительство и ремонтВодоснабжение для дома и садаКрепеж для монтажа трубХомуты и стяжки | C10: Строительство и ремонт | D10: Водоснабжение для дома и сада | E10: Крепеж для монтажа труб | F10: Хомуты и стяжки | I10: 0.2 | J10: 0.2 | K10: 0.2 | L10: 0 | M10: 0 | N10: 0 | O10: 0.2 | P10: 0.2 | Q10: 0.2
A11: 24 | B11: =C11&D11&E11&F11&G11&H11 -> Строительство и ремонтИнструментыЭлектроинструментыЭлектрорубанки | C11: Строительство и ремонт | D11: Инструменты | E11: Электроинструменты | F11: Электрорубанки | I11: 0.15 | J11: 0.15 | K11: 0.15 | L11: 0 | M11: 0 | N11: 0 | O11: 0.15 | P11: 0.15 | Q11: 0.15
A12: 25 | B12: =C12&D12&E12&F12&G12&H12 -> Строительство и ремонтИнструментыНаборы ручных инструментов | C12: Строительство и ремонт | D12: Инструменты | E12: Наборы ручных инструментов | I12: 0.15 | J12: 0.15 | K12: 0.15 | L12: 0 | M12: 0 | N12: 0 | O12: 0.15 | P12: 0.15 | Q12: 0.15
A13: 26 | B13: =C13&D13&E13&F13&G13&H13 -> Строительство и ремонтСантехникаАрматура и аксессуары для сантехникиРемкомплекты и запчасти | C13: Строительство и ремонт | D13: Сантехника | E13: Арматура и аксессуары для сантехники | F13: Ремкомплекты и запчасти | I13: 0.25 | J13: 0.25 | K13: 0.25 | L13: 0 | M13: 0 | N13: 0 | O13: 0.25 | P13: 0.25 | Q13: 0.25
A14: 28 | B14: =C14&D14&E14&F14&G14&H14 -> ЗдоровьеПрезервативы, лубриканты и пролонгаторыПрезервативы | C14: Здоровье | D14: Презервативы, лубриканты и пролонгаторы | E14: Презервативы | I14: 0.25 | J14: 0.25 | K14: 0.25 | L14: 0 | M14: 0 | N14: 0 | O14: 0.25 | P14: 0.25 | Q14: 0.25
A15: 62 | B15: =C15&D15&E15&F15&G15&H15 -> Продукты питанияВода, соки, напиткиЭнергетические напитки | C15: Продукты питания | D15: Вода, соки, напитки | E15: Энергетические напитки | I15: 0.15 | J15: 0.15 | K15: 0.15 | L15: 0.02 | M15: 0.02 | N15: 0.02 | O15: 0.13 | P15: 0.13 | Q15: 0.13
A16: 63 | B16: =C16&D16&E16&F16&G16&H16 -> МебельОфисная и компьютерная мебельСейфы | C16: Мебель | D16: Офисная и компьютерная мебель | E16: Сейфы | I16: 0.15 | J16: 0.15 | K16: 0.15 | L16: 0 | M16: 0 | N16: 0 | O16: 0.15 | P16: 0.15 | Q16: 0.15
A17: 64 | B17: =C17&D17&E17&F17&G17&H17 -> Продукты питанияМука, сахар и сольСоль | C17: Продукты питания | D17: Мука, сахар и соль | E17: Соль | I17: 0.15 | J17: 0.15 | K17: 0.15 | L17: 0.01 | M17: 0.01 | N17: 0.01 | O17: 0.14 | P17: 0.14 | Q17: 0.14
A18: 68 | B18: =C18&D18&E18&F18&G18&H18 -> КанцтоварыПисьменные принадлежностиТочилки для карандашей | C18: Канцтовары | D18: Письменные принадлежности | E18: Точилки для карандашей | I18: 0.2 | J18: 0.2 | K18: 0.2 | L18: 0.105 | M18: 0.105 | N18: 0.105 | O18: 0.095 | P18: 0.095 | Q18: 0.095
A19: 69 | B19: =C19&D19&E19&F19&G19&H19 -> Продукты питанияМакароны, крупы и сухие завтракиКрупы и бобовыеОвсяная | C19: Продукты питания | D19: Макароны, крупы и сухие завтраки | E19: Крупы и бобовые | F19: Овсяная | I19: 0.12 | J19: 0.12 | K19: 0.12 | L19: 0.045 | M19: 0.045 | N19: 0.045 | O19: 0.075 | P19: 0.075 | Q19: 0.075
A20: 70 | B20: =C20&D20&E20&F20&G20&H20 -> Продукты питанияМакароны, крупы и сухие завтракиКрупы и бобовыеПшено | C20: Продукты питания | D20: Макароны, крупы и сухие завтраки | E20: Крупы и бобовые | F20: Пшено | I20: 0.12 | J20: 0.12 | K20: 0.12 | L20: 0.045 | M20: 0.045 | N20: 0.045 | O20: 0.075 | P20: 0.075 | Q20: 0.075
A21: 71 | B21: =C21&D21&E21&F21&G21&H21 -> Продукты питанияЗдоровое питаниеМорские водоросли | C21: Продукты питания | D21: Здоровое питание | E21: Морские водоросли | I21: 0.15 | J21: 0.15 | K21: 0.15 | L21: 0.01 | M21: 0.01 | N21: 0.01 | O21: 0.14 | P21: 0.14 | Q21: 0.14
A22: 72 | B22: =C22&D22&E22&F22&G22&H22 -> Продукты питанияМед, варенье, сладкая консервацияСиропы и топпинги | C22: Продукты питания | D22: Мед, варенье, сладкая консервация | E22: Сиропы и топпинги | I22: 0.15 | J22: 0.15 | K22: 0.15 | L22: 0.02 | M22: 0.02 | N22: 0.02 | O22: 0.13 | P22: 0.13 | Q22: 0.13
A23: 73 | B23: =C23&D23&E23&F23&G23&H23 -> Продукты питанияМакароны, крупы и сухие завтракиКрупы и бобовыеПерловка | C23: Продукты питания | D23: Макароны, крупы и сухие завтраки | E23: Крупы и бобовые | F23: Перловка | I23: 0.12 | J23: 0.12 | K23: 0.12 | L23: 0.045 | M23: 0.045 | N23: 0.045 | O23: 0.075 | P23: 0.075 | Q23: 0.075
A24: 77 | B24: =C24&D24&E24&F24&G24&H24 -> АвтотоварыЭлектроника для автоАлкотестеры | C24: Автотовары | D24: Электроника для авто | E24: Алкотестеры | I24: 0.2 | J24: 0.2 | K24: 0.2 | L24: 0 | M24: 0 | N24: 0 | O24: 0.2 | P24: 0.2 | Q24: 0.2
A25: 78 | B25: =C25&D25&E25&F25&G25&H25 -> Бытовая техникаКрупная бытовая техникаПлитыКомбинированные плиты | C25: Бытовая техника | D25: Крупная бытовая техника | E25: Плиты | F25: Комбинированные плиты | I25: 0.1 | J25: 0.1 | K25: 0.1 | L25: 0 | M25: 0 | N25: 0 | O25: 0.1 | P25: 0.1 | Q25: 0.1
A26: 81 | B26: =C26&D26&E26&F26&G26&H26 -> Бытовая техникаКрупная бытовая техникаПлитыЭлектрические плиты | C26: Бытовая техника | D26: Крупная бытовая техника | E26: Плиты | F26: Электрические плиты | I26: 0.1 | J26: 0.1 | K26: 0.1 | L26: 0 | M26: 0 | N26: 0 | O26: 0.1 | P26: 0.1 | Q26: 0.1
A27: 82 | B27: =C27&D27&E27&F27&G27&H27 -> Бытовая техникаКрупная бытовая техникаХолодильники и морозильникиХолодильники | C27: Бытовая техника | D27: Крупная бытовая техника | E27: Холодильники и морозильники | F27: Холодильники | I27: 0.1 | J27: 0.1 | K27: 0.1 | L27: 0 | M27: 0 | N27: 0 | O27: 0.1 | P27: 0.1 | Q27: 0.1
A28: 83 | B28: =C28&D28&E28&F28&G28&H28 -> Бытовая техникаКрупная бытовая техникаХолодильники и морозильникиМорозильники | C28: Бытовая техника | D28: Крупная бытовая техника | E28: Холодильники и морозильники | F28: Морозильники | I28: 0.1 | J28: 0.1 | K28: 0.1 | L28: 0 | M28: 0 | N28: 0 | O28: 0.1 | P28: 0.1 | Q28: 0.1
A29: 84 | B29: =C29&D29&E29&F29&G29&H29 -> Бытовая техникаКрупная бытовая техникаХолодильники и морозильникиХолодильные шкафы | C29: Бытовая техника | D29: Крупная бытовая техника | E29: Холодильники и морозильники | F29: Холодильные шкафы | I29: 0.1 | J29: 0.1 | K29: 0.1 | L29: 0 | M29: 0 | N29: 0 | O29: 0.1 | P29: 0.1 | Q29: 0.1
A30: 85 | B30: =C30&D30&E30&F30&G30&H30 -> Бытовая техникаКрупная бытовая техникаХолодильники и морозильникиВинные шкафы | C30: Бытовая техника | D30: Крупная бытовая техника | E30: Холодильники и морозильники | F30: Винные шкафы | I30: 0.1 | J30: 0.1 | K30: 0.1 | L30: 0 | M30: 0 | N30: 0 | O30: 0.1 | P30: 0.1 | Q30: 0.1
A31: 86 | B31: =C31&D31&E31&F31&G31&H31 -> Хобби и творчествоПазлы, мозаика и фрескаПазлы | C31: Хобби и творчество | D31: Пазлы, мозаика и фреска | E31: Пазлы | I31: 0.22 | J31: 0.22 | K31: 0.22 | L31: 0 | M31: 0 | N31: 0 | O31: 0.22 | P31: 0.22 | Q31: 0.22
A32: 88 | B32: =C32&D32&E32&F32&G32&H32 -> Продукты питанияПродукты для выпечки и десертовПищевые добавкиПищевые красители и ароматизаторы | C32: Продукты питания | D32: Продукты для выпечки и десертов | E32: Пищевые добавки | F32: Пищевые красители и ароматизаторы | I32: 0.15 | J32: 0.15 | K32: 0.15 | L32: 0.035 | M32: 0.035 | N32: 0.035 | O32: 0.115 | P32: 0.115 | Q32: 0.115
A33: 90 | B33: =C33&D33&E33&F33&G33&H33 -> Строительство и ремонтОтоплениеРасширительные баки | C33: Строительство и ремонт | D33: Отопление | E33: Расширительные баки | I33: 0.22 | J33: 0.22 | K33: 0.22 | L33: 0 | M33: 0 | N33: 0 | O33: 0.22 | P33: 0.22 | Q33: 0.22
A34: 114 | B34: =C34&D34&E34&F34&G34&H34 -> Продукты питанияЗдоровое питаниеУрбеч | C34: Продукты питания | D34: Здоровое питание | E34: Урбеч | I34: 0.22 | J34: 0.22 | K34: 0.22 | L34: 0 | M34: 0 | N34: 0 | O34: 0.22 | P34: 0.22 | Q34: 0.22
A35: 115 | B35: =C35&D35&E35&F35&G35&H35 -> Продукты питанияМед, варенье, сладкая консервацияВаренье, джемы и протертые ягоды | C35: Продукты питания | D35: Мед, варенье, сладкая консервация | E35: Варенье, джемы и протертые ягоды | I35: 0.15 | J35: 0.15 | K35: 0.15 | L35: 0.005 | M35: 0.005 | N35: 0.005 | O35: 0.145 | P35: 0.145 | Q35: 0.145
A36: 125 | B36: =C36&D36&E36&F36&G36&H36 -> Строительство и ремонтВодоснабжение для дома и садаЗапорно-регулирующая арматураШаровые краны | C36: Строительство и ремонт | D36: Водоснабжение для дома и сада | E36: Запорно-регулирующая арматура | F36: Шаровые краны | I36: 0.2 | J36: 0.2 | K36: 0.2 | L36: 0 | M36: 0 | N36: 0 | O36: 0.2 | P36: 0.2 | Q36: 0.2
A37: 126 | B37: =C37&D37&E37&F37&G37&H37 -> Строительство и ремонтОтоплениеСепараторы воздуха и шлама | C37: Строительство и ремонт | D37: Отопление | E37: Сепараторы воздуха и шлама | I37: 0.25 | J37: 0.25 | K37: 0.25 | L37: 0 | M37: 0 | N37: 0 | O37: 0.25 | P37: 0.25 | Q37: 0.25
A38: 129 | B38: =C38&D38&E38&F38&G38&H38 -> Строительство и ремонтОтоплениеТеплые полыВодяной тёплый полРегуляторы температуры для тёплых полов | C38: Строительство и ремонт | D38: Отопление | E38: Теплые полы | F38: Водяной тёплый пол | G38: Регуляторы температуры для тёплых полов | I38: 0.25 | J38: 0.25 | K38: 0.25 | L38: 0 | M38: 0 | N38: 0 | O38: 0.25 | P38: 0.25 | Q38: 0.25
A39: 130 | B39: =C39&D39&E39&F39&G39&H39 -> Строительство и ремонтОтоплениеТеплые полыВодяной тёплый полКоллекторные группы | C39: Строительство и ремонт | D39: Отопление | E39: Теплые полы | F39: Водяной тёплый пол | G39: Коллекторные группы | I39: 0.25 | J39: 0.25 | K39: 0.25 | L39: 0 | M39: 0 | N39: 0 | O39: 0.25 | P39: 0.25 | Q39: 0.25
A40: 132 | B40: =C40&D40&E40&F40&G40&H40 -> Продукты питанияКонсервацияКонсервированные блюда | C40: Продукты питания | D40: Консервация | E40: Консервированные блюда | I40: 0.15 | J40: 0.15 | K40: 0.15 | L40: 0 | M40: 0 | N40: 0 | O40: 0.15 | P40: 0.15 | Q40: 0.15
A41: 134 | B41: =C41&D41&E41&F41&G41&H41 -> Продукты питанияМасла, соусы и приправыПриправы | C41: Продукты питания | D41: Масла, соусы и приправы | E41: Приправы | I41: 0.15 | J41: 0.15 | K41: 0.15 | L41: 0.01 | M41: 0.01 | N41: 0.01 | O41: 0.14 | P41: 0.14 | Q41: 0.14
A42: 135 | B42: =C42&D42&E42&F42&G42&H42 -> Продукты питанияМука, сахар и сольСахар | C42: Продукты питания | D42: Мука, сахар и соль | E42: Сахар | I42: 0.05 | J42: 0.05 | K42: 0.05 | L42: 0.01 | M42: 0.01 | N42: 0.01 | O42: 0.04 | P42: 0.04 | Q42: 0.04
A43: 136 | B43: =C43&D43&E43&F43&G43&H43 -> Продукты питанияМука, сахар и сольМука | C43: Продукты питания | D43: Мука, сахар и соль | E43: Мука | I43: 0.15 | J43: 0.15 | K43: 0.15 | L43: 0.01 | M43: 0.01 | N43: 0.01 | O43: 0.14 | P43: 0.14 | Q43: 0.14
A44: 138 | B44: =C44&D44&E44&F44&G44&H44 -> Продукты питанияМасла, соусы и приправыСоусыУксус | C44: Продукты питания | D44: Масла, соусы и приправы | E44: Соусы | F44: Уксус | I44: 0.15 | J44: 0.15 | K44: 0.15 | L44: 0.01 | M44: 0.01 | N44: 0.01 | O44: 0.14 | P44: 0.14 | Q44: 0.14
A45: 142 | B45: =C45&D45&E45&F45&G45&H45 -> Продукты питанияМакароны, крупы и сухие завтракиМакароны | C45: Продукты питания | D45: Макароны, крупы и сухие завтраки | E45: Макароны | I45: 0.12 | J45: 0.12 | K45: 0.12 | L45: 0.045 | M45: 0.045 | N45: 0.045 | O45: 0.075 | P45: 0.075 | Q45: 0.075
A46: 143 | B46: =C46&D46&E46&F46&G46&H46 -> Продукты питанияЧай, кофе и какаоЧай с добавками | C46: Продукты питания | D46: Чай, кофе и какао | E46: Чай с добавками | I46: 0.17 | J46: 0.17 | K46: 0.17 | L46: 0.01 | M46: 0.01 | N46: 0.01 | O46: 0.16 | P46: 0.16 | Q46: 0.16
A47: 326 | B47: =C47&D47&E47&F47&G47&H47 -> Продукты питанияСнеки, орехи и семечкиОрехи | C47: Продукты питания | D47: Снеки, орехи и семечки | E47: Орехи | I47: 0.15 | J47: 0.15 | K47: 0.15 | L47: 0.01 | M47: 0.01 | N47: 0.01 | O47: 0.14 | P47: 0.14 | Q47: 0.14
A48: 329 | B48: =C48&D48&E48&F48&G48&H48 -> Продукты питанияЗдоровое питаниеБальзамы, тоники, эликсиры | C48: Продукты питания | D48: Здоровое питание | E48: Бальзамы, тоники, эликсиры | I48: 0.15 | J48: 0.15 | K48: 0.15 | L48: 0.01 | M48: 0.01 | N48: 0.01 | O48: 0.14 | P48: 0.14 | Q48: 0.14
A49: 356 | B49: =C49&D49&E49&F49&G49&H49 -> Продукты питанияВыпечка и сладостиШоколад | C49: Продукты питания | D49: Выпечка и сладости | E49: Шоколад | I49: 0.2 | J49: -% | K49: 0.2 | L49: 0.015 | M49: 0.015 | N49: 0.015 | O49: 0.185 | P49: -% | Q49: 0.185
A50: 366 | B50: =C50&D50&E50&F50&G50&H50 -> Продукты питанияЗдоровое питаниеХлебцы | C50: Продукты питания | D50: Здоровое питание | E50: Хлебцы | I50: 0.15 | J50: 0.15 | K50: 0.15 | L50: 0 | M50: 0 | N50: 0 | O50: 0.15 | P50: 0.15 | Q50: 0.15
A51: 369 | B51: =C51&D51&E51&F51&G51&H51 -> Продукты питанияВыпечка и сладостиБатончики | C51: Продукты питания | D51: Выпечка и сладости | E51: Батончики | I51: 0.2 | J51: -% | K51: 0.2 | L51: 0.015 | M51: 0.015 | N51: 0.015 | O51: 0.185 | P51: -% | Q51: 0.185
A52: 531 | B52: =C52&D52&E52&F52&G52&H52 -> Продукты питанияКонсервацияМясные консервы | C52: Продукты питания | D52: Консервация | E52: Мясные консервы | I52: 0.15 | J52: 0.15 | K52: 0.15 | L52: 0.005 | M52: 0.005 | N52: 0.005 | O52: 0.145 | P52: 0.145 | Q52: 0.145
A53: 555 | B53: =C53&D53&E53&F53&G53&H53 -> Продукты питанияЧай, кофе и какаоЦикорий | C53: Продукты питания | D53: Чай, кофе и какао | E53: Цикорий | I53: 0.17 | J53: 0.17 | K53: 0.17 | L53: 0 | M53: 0 | N53: 0 | O53: 0.17 | P53: 0.17 | Q53: 0.17
A54: 1892 | B54: =C54&D54&E54&F54&G54&H54 -> Продукты питанияВыпечка и сладостиЖевательные резинки | C54: Продукты питания | D54: Выпечка и сладости | E54: Жевательные резинки | I54: 0.2 | J54: 0.2 | K54: 0.2 | L54: 0.015 | M54: 0.015 | N54: 0.015 | O54: 0.185 | P54: 0.185 | Q54: 0.185
A55: 1915 | B55: =C55&D55&E55&F55&G55&H55 -> Продукты питанияВыпечка и сладостиШоколадная, ореховая паста | C55: Продукты питания | D55: Выпечка и сладости | E55: Шоколадная, ореховая паста | I55: 0.2 | J55: 0.2 | K55: 0.2 | L55: 0.015 | M55: 0.015 | N55: 0.015 | O55: 0.185 | P55: 0.185 | Q55: 0.185
A56: 2477 | B56: =C56&D56&E56&F56&G56&H56 -> Продукты питанияКонсервацияКонсервированные овощи | C56: Продукты питания | D56: Консервация | E56: Консервированные овощи | I56: 0.15 | J56: 0.15 | K56: 0.15 | L56: 0.005 | M56: 0.005 | N56: 0.005 | O56: 0.145 | P56: 0.145 | Q56: 0.145
A57: 2481 | B57: =C57&D57&E57&F57&G57&H57 -> Продукты питанияСнеки, орехи и семечкиКурт | C57: Продукты питания | D57: Снеки, орехи и семечки | E57: Курт | I57: 0.22 | J57: 0.22 | K57: 0.22 | L57: 0.01 | M57: 0.01 | N57: 0.01 | O57: 0.21 | P57: 0.21 | Q57: 0.21
A58: 2570 | B58: =C58&D58&E58&F58&G58&H58 -> Красота и уходЛичная гигиенаВатная продукцияВлажные салфетки | C58: Красота и уход | D58: Личная гигиена | E58: Ватная продукция | F58: Влажные салфетки | I58: 0.2 | J58: 0.2 | K58: 0.2 | L58: 0.02 | M58: 0.02 | N58: 0.02 | O58: 0.18 | P58: 0.18 | Q58: 0.18
A59: 2571 | B59: =C59&D59&E59&F59&G59&H59 -> Красота и уходЛичная гигиенаГигиена полости ртаЗубные нити | C59: Красота и уход | D59: Личная гигиена | E59: Гигиена полости рта | F59: Зубные нити | I59: 0.2 | J59: 0.2 | K59: 0.2 | L59: 0.02 | M59: 0.02 | N59: 0.02 | O59: 0.18 | P59: 0.18 | Q59: 0.18
A60: 2572 | B60: =C60&D60&E60&F60&G60&H60 -> Красота и уходЛичная гигиенаГигиена полости ртаЭлектрические зубные щетки | C60: Красота и уход | D60: Личная гигиена | E60: Гигиена полости рта | F60: Электрические зубные щетки | I60: 0.2 | J60: 0.2 | K60: 0.2 | L60: 0.01 | M60: 0.01 | N60: 0.01 | O60: 0.19 | P60: 0.19 | Q60: 0.19
A61: 2573 | B61: =C61&D61&E61&F61&G61&H61 -> Красота и уходЛичная гигиенаГигиена полости ртаНасадки для электрических зубных щеток и ирригаторов | C61: Красота и уход | D61: Личная гигиена | E61: Гигиена полости рта | F61: Насадки для электрических зубных щеток и ирригаторов | I61: 0.2 | J61: 0.2 | K61: 0.2 | L61: 0.01 | M61: 0.01 | N61: 0.01 | O61: 0.19 | P61: 0.19 | Q61: 0.19
A62: 2574 | B62: =C62&D62&E62&F62&G62&H62 -> Красота и уходЛичная гигиенаГигиена полости ртаАксессуары для электрических зубных щеток и ирригаторов | C62: Красота и уход | D62: Личная гигиена | E62: Гигиена полости рта | F62: Аксессуары для электрических зубных щеток и ирригаторов | I62: 0.2 | J62: 0.2 | K62: 0.2 | L62: 0.01 | M62: 0.01 | N62: 0.01 | O62: 0.19 | P62: 0.19 | Q62: 0.19
A63: 2575 | B63: =C63&D63&E63&F63&G63&H63 -> Детские товарыКоляски и автокреслаАксессуары для колясок и автокресел | C63: Детские товары | D63: Коляски и автокресла | E63: Аксессуары для колясок и автокресел | I63: 0.25 | J63: 0.25 | K63: 0.25 | L63: 0 | M63: 0 | N63: 0 | O63: 0.25 | P63: 0.25 | Q63: 0.25
A64: 2576 | B64: =C64&D64&E64&F64&G64&H64 -> Детские товарыИгрушки и игрыИгрушки для купания | C64: Детские товары | D64: Игрушки и игры | E64: Игрушки для купания | I64: 0.3 | J64: 0.3 | K64: 0.3 | L64: 0 | M64: 0 | N64: 0 | O64: 0.3 | P64: 0.3 | Q64: 0.3
A65: 2577 | B65: =C65&D65&E65&F65&G65&H65 -> Детские товарыТовары для кормленияПосуда и принадлежности для кормленияДетские тарелки и миски | C65: Детские товары | D65: Товары для кормления | E65: Посуда и принадлежности для кормления | F65: Детские тарелки и миски | I65: 0.2 | J65: 0.2 | K65: 0.2 | L65: 0.015 | M65: 0.015 | N65: 0.015 | O65: 0.185 | P65: 0.185 | Q65: 0.185
A66: 2578 | B66: =C66&D66&E66&F66&G66&H66 -> Детские товарыГигиена и подгузникиГигиена полости ртаДетские зубные пасты | C66: Детские товары | D66: Гигиена и подгузники | E66: Гигиена полости рта | F66: Детские зубные пасты | I66: 0.2 | J66: 0.2 | K66: 0.2 | L66: 0 | M66: 0 | N66: 0 | O66: 0.2 | P66: 0.2 | Q66: 0.2
A67: 2580 | B67: =C67&D67&E67&F67&G67&H67 -> Детские товарыИгрушки и игрыКонструкторыДеревянные | C67: Детские товары | D67: Игрушки и игры | E67: Конструкторы | F67: Деревянные | I67: 0.2 | J67: 0.2 | K67: 0.2 | L67: 0.03 | M67: 0.03 | N67: 0.03 | O67: 0.17 | P67: 0.17 | Q67: 0.17
A68: 2581 | B68: =C68&D68&E68&F68&G68&H68 -> Детские товарыИгрушки и игрыКонструкторыМагнитные | C68: Детские товары | D68: Игрушки и игры | E68: Конструкторы | F68: Магнитные | I68: 0.2 | J68: 0.2 | K68: 0.2 | L68: 0.03 | M68: 0.03 | N68: 0.03 | O68: 0.17 | P68: 0.17 | Q68: 0.17
A69: 2582 | B69: =C69&D69&E69&F69&G69&H69 -> Детские товарыИгрушки и игрыКонструкторыБлочные | C69: Детские товары | D69: Игрушки и игры | E69: Конструкторы | F69: Блочные | I69: 0.2 | J69: 0.2 | K69: 0.2 | L69: 0 | M69: 0 | N69: 0 | O69: 0.2 | P69: 0.2 | Q69: 0.2
A70: 2583 | B70: =C70&D70&E70&F70&G70&H70 -> Детские товарыИгрушки и игрыКонструкторыМеталлические | C70: Детские товары | D70: Игрушки и игры | E70: Конструкторы | F70: Металлические | I70: 0.2 | J70: 0.2 | K70: 0.2 | L70: 0.03 | M70: 0.03 | N70: 0.03 | O70: 0.17 | P70: 0.17 | Q70: 0.17
A71: 2584 | B71: =C71&D71&E71&F71&G71&H71 -> Детские товарыИгрушки и игрыДеревянные игрушки | C71: Детские товары | D71: Игрушки и игры | E71: Деревянные игрушки | I71: 0.2 | J71: 0.2 | K71: 0.2 | L71: 0.02 | M71: 0.02 | N71: 0.02 | O71: 0.18 | P71: 0.18 | Q71: 0.18
A72: 2585 | B72: =C72&D72&E72&F72&G72&H72 -> Детские товарыИгрушки и игрыКукольные домики | C72: Детские товары | D72: Игрушки и игры | E72: Кукольные домики | I72: 0.2 | J72: 0.2 | K72: 0.2 | L72: 0.03 | M72: 0.03 | N72: 0.03 | O72: 0.17 | P72: 0.17 | Q72: 0.17
A73: 2586 | B73: =C73&D73&E73&F73&G73&H73 -> Детские товарыИгрушки и игрыИгрушки - антистресс | C73: Детские товары | D73: Игрушки и игры | E73: Игрушки - антистресс | I73: 0.2 | J73: 0.2 | K73: 0.2 | L73: 0 | M73: 0 | N73: 0 | O73: 0.2 | P73: 0.2 | Q73: 0.2
A74: 2587 | B74: =C74&D74&E74&F74&G74&H74 -> Детские товарыИгрушки и игрыФигурки и аксессуары | C74: Детские товары | D74: Игрушки и игры | E74: Фигурки и аксессуары | I74: 0.2 | J74: 0.2 | K74: 0.2 | L74: 0.03 | M74: 0.03 | N74: 0.03 | O74: 0.17 | P74: 0.17 | Q74: 0.17
A75: 2588 | B75: =C75&D75&E75&F75&G75&H75 -> Детские товарыИгрушки и игрыРазвивающие и обучающие игрушкиСюжетно-ролевые игры | C75: Детские товары | D75: Игрушки и игры | E75: Развивающие и обучающие игрушки | F75: Сюжетно-ролевые игры | I75: 0.2 | J75: 0.2 | K75: 0.2 | L75: 0 | M75: 0 | N75: 0 | O75: 0.2 | P75: 0.2 | Q75: 0.2
A76: 2590 | B76: =C76&D76&E76&F76&G76&H76 -> Спорт и отдыхВодный спорт и отдых на водеПлаваниеКруги и матрасыМатрасы для плавания | C76: Спорт и отдых | D76: Водный спорт и отдых на воде | E76: Плавание | F76: Круги и матрасы | G76: Матрасы для плавания | I76: 0.25 | J76: 0.25 | K76: 0.25 | L76: 0.01 | M76: 0.01 | N76: 0.01 | O76: 0.24 | P76: 0.24 | Q76: 0.24
A77: 2592 | B77: =C77&D77&E77&F77&G77&H77 -> Детские товарыДетский спорт и активный отдыхИгры на улицеВоздушные змеи | C77: Детские товары | D77: Детский спорт и активный отдых | E77: Игры на улице | F77: Воздушные змеи | I77: 0.25 | J77: 0.25 | K77: 0.25 | L77: 0.02 | M77: 0.02 | N77: 0.02 | O77: 0.23 | P77: 0.23 | Q77: 0.23
A78: 2593 | B78: =C78&D78&E78&F78&G78&H78 -> Детские товарыДетский спорт и активный отдыхИгры на улицеБумеранги | C78: Детские товары | D78: Детский спорт и активный отдых | E78: Игры на улице | F78: Бумеранги | I78: 0.25 | J78: 0.25 | K78: 0.25 | L78: 0 | M78: 0 | N78: 0 | O78: 0.25 | P78: 0.25 | Q78: 0.25
A79: 2594 | B79: =C79&D79&E79&F79&G79&H79 -> Детские товарыДетский спорт и активный отдыхИгры на улицеФрисби | C79: Детские товары | D79: Детский спорт и активный отдых | E79: Игры на улице | F79: Фрисби | I79: 0.25 | J79: 0.25 | K79: 0.25 | L79: 0.02 | M79: 0.02 | N79: 0.02 | O79: 0.23 | P79: 0.23 | Q79: 0.23
A80: 2595 | B80: =C80&D80&E80&F80&G80&H80 -> Детские товарыДетский спорт и активный отдыхИгры на улицеСпортивные игры | C80: Детские товары | D80: Детский спорт и активный отдых | E80: Игры на улице | F80: Спортивные игры | I80: 0.2 | J80: 0.2 | K80: 0.2 | L80: 0 | M80: 0 | N80: 0 | O80: 0.2 | P80: 0.2 | Q80: 0.2
A81: 2597 | B81: =C81&D81&E81&F81&G81&H81 -> Детские товарыИгрушки и игрыРазвивающие и обучающие игрушкиОбучающие игрушки и игры | C81: Детские товары | D81: Игрушки и игры | E81: Развивающие и обучающие игрушки | F81: Обучающие игрушки и игры | I81: 0.2 | J81: 0.2 | K81: 0.2 | L81: 0.03 | M81: 0.03 | N81: 0.03 | O81: 0.17 | P81: 0.17 | Q81: 0.17
A82: 2598 | B82: =C82&D82&E82&F82&G82&H82 -> Строительство и ремонтДвери, окна и комплектующиеРольставни | C82: Строительство и ремонт | D82: Двери, окна и комплектующие | E82: Рольставни | I82: -% | J82: -% | K82: 0.1 | L82: -% | M82: -% | N82: 0 | O82: -% | P82: -% | Q82: 0.1
A83: 2599 | B83: =C83&D83&E83&F83&G83&H83 -> ОдеждаЖенская одеждаКупальники и пляжная одеждаРаздельные купальники | C83: Одежда | D83: Женская одежда | E83: Купальники и пляжная одежда | F83: Раздельные купальники | I83: 0.25 | J83: 0.25 | K83: 0.25 | L83: 0 | M83: 0 | N83: 0 | O83: 0.25 | P83: 0.25 | Q83: 0.25
A84: 2600 | B84: =C84&D84&E84&F84&G84&H84 -> ОдеждаЖенская одеждаКупальники и пляжная одеждаПляжные платья и туники | C84: Одежда | D84: Женская одежда | E84: Купальники и пляжная одежда | F84: Пляжные платья и туники | I84: 0.25 | J84: 0.25 | K84: 0.25 | L84: 0 | M84: 0 | N84: 0 | O84: 0.25 | P84: 0.25 | Q84: 0.25
A85: 2601 | B85: =C85&D85&E85&F85&G85&H85 -> ОдеждаЖенская одеждаНижнее бельёМайки и бельевые топы | C85: Одежда | D85: Женская одежда | E85: Нижнее бельё | F85: Майки и бельевые топы | I85: 0.25 | J85: 0.25 | K85: 0.25 | L85: 0 | M85: 0 | N85: 0 | O85: 0.25 | P85: 0.25 | Q85: 0.25
A86: 2603 | B86: =C86&D86&E86&F86&G86&H86 -> ОдеждаМужская одеждаДомашняя одеждаДомашние комбинезоны | C86: Одежда | D86: Мужская одежда | E86: Домашняя одежда | F86: Домашние комбинезоны | I86: 0.25 | J86: 0.25 | K86: 0.25 | L86: 0 | M86: 0 | N86: 0 | O86: 0.25 | P86: 0.25 | Q86: 0.25
A87: 2605 | B87: =C87&D87&E87&F87&G87&H87 -> ОдеждаОдежда для мальчиковНоскиКолготки | C87: Одежда | D87: Одежда для мальчиков | E87: Носки | F87: Колготки | I87: 0.25 | J87: 0.25 | K87: 0.25 | L87: 0 | M87: 0 | N87: 0 | O87: 0.25 | P87: 0.25 | Q87: 0.25
A88: 2607 | B88: =C88&D88&E88&F88&G88&H88 -> АксессуарыЖенские аксессуарыЧасы и ремешкиЧасы | C88: Аксессуары | D88: Женские аксессуары | E88: Часы и ремешки | F88: Часы | I88: 0.25 | J88: 0.25 | K88: 0.25 | L88: 0 | M88: 0 | N88: 0 | O88: 0.25 | P88: 0.25 | Q88: 0.25
A89: 2608 | B89: =C89&D89&E89&F89&G89&H89 -> АксессуарыЖенские аксессуарыЧасы и ремешкиРемешки для часов | C89: Аксессуары | D89: Женские аксессуары | E89: Часы и ремешки | F89: Ремешки для часов | I89: 0.3 | J89: 0.3 | K89: 0.3 | L89: 0 | M89: 0 | N89: 0 | O89: 0.3 | P89: 0.3 | Q89: 0.3
A90: 2610 | B90: =C90&D90&E90&F90&G90&H90 -> АксессуарыМужские аксессуарыЧасы и ремешкиЧасы | C90: Аксессуары | D90: Мужские аксессуары | E90: Часы и ремешки | F90: Часы | I90: 0.25 | J90: 0.25 | K90: 0.25 | L90: 0 | M90: 0 | N90: 0 | O90: 0.25 | P90: 0.25 | Q90: 0.25
A91: 2611 | B91: =C91&D91&E91&F91&G91&H91 -> Строительство и ремонтРасходные материалы и оснасткаОснасткаПринадлежностиПринадлежности для инструментов | C91: Строительство и ремонт | D91: Расходные материалы и оснастка | E91: Оснастка | F91: Принадлежности | G91: Принадлежности для инструментов | I91: 0.22 | J91: 0.22 | K91: 0.22 | L91: 0 | M91: 0 | N91: 0 | O91: 0.22 | P91: 0.22 | Q91: 0.22
A92: 2614 | B92: =C92&D92&E92&F92&G92&H92 -> КанцтоварыТовары для школы и обученияПеналы | C92: Канцтовары | D92: Товары для школы и обучения | E92: Пеналы | I92: 0.2 | J92: 0.2 | K92: 0.2 | L92: 0 | M92: 0 | N92: 0 | O92: 0.2 | P92: 0.2 | Q92: 0.2
A93: 2615 | B93: =C93&D93&E93&F93&G93&H93 -> АвтотоварыАксессуары и принадлежностиПрочие автомобильные аксессуары | C93: Автотовары | D93: Аксессуары и принадлежности | E93: Прочие автомобильные аксессуары | I93: 0.25 | J93: 0.25 | K93: 0.25 | L93: 0 | M93: 0 | N93: 0 | O93: 0.25 | P93: 0.25 | Q93: 0.25
A94: 2622 | B94: =C94&D94&E94&F94&G94&H94 -> Строительство и ремонтОсвещениеСветомузыка | C94: Строительство и ремонт | D94: Освещение | E94: Светомузыка | I94: 0.22 | J94: 0.22 | K94: 0.22 | L94: 0 | M94: 0 | N94: 0 | O94: 0.22 | P94: 0.22 | Q94: 0.22
A95: 2625 | B95: =C95&D95&E95&F95&G95&H95 -> Туризм, рыбалка и охотаТуризм и отдых на природеАксессуары для туризма и отдыха | C95: Туризм, рыбалка и охота | D95: Туризм и отдых на природе | E95: Аксессуары для туризма и отдыха | I95: 0.25 | J95: 0.25 | K95: 0.25 | L95: 0 | M95: 0 | N95: 0 | O95: 0.25 | P95: 0.25 | Q95: 0.25
A96: 2627 | B96: =C96&D96&E96&F96&G96&H96 -> Туризм, рыбалка и охотаТуризм и отдых на природеКотелки и костровые треноги | C96: Туризм, рыбалка и охота | D96: Туризм и отдых на природе | E96: Котелки и костровые треноги | I96: 0.25 | J96: 0.25 | K96: 0.25 | L96: 0 | M96: 0 | N96: 0 | O96: 0.25 | P96: 0.25 | Q96: 0.25
A97: 2628 | B97: =C97&D97&E97&F97&G97&H97 -> Туризм, рыбалка и охотаТуризм и отдых на природеПоходная посуда | C97: Туризм, рыбалка и охота | D97: Туризм и отдых на природе | E97: Походная посуда | I97: 0.25 | J97: 0.25 | K97: 0.25 | L97: 0 | M97: 0 | N97: 0 | O97: 0.25 | P97: 0.25 | Q97: 0.25
A98: 2629 | B98: =C98&D98&E98&F98&G98&H98 -> Туризм, рыбалка и охотаТуризм и отдых на природеФляги и питьевые системыФляги | C98: Туризм, рыбалка и охота | D98: Туризм и отдых на природе | E98: Фляги и питьевые системы | F98: Фляги | I98: 0.25 | J98: 0.25 | K98: 0.25 | L98: 0 | M98: 0 | N98: 0 | O98: 0.25 | P98: 0.25 | Q98: 0.25
A99: 2631 | B99: =C99&D99&E99&F99&G99&H99 -> Красота и уходМакияжАксессуары для макияжаСпонжи и аппликаторы | C99: Красота и уход | D99: Макияж | E99: Аксессуары для макияжа | F99: Спонжи и аппликаторы | I99: 0.3 | J99: 0.3 | K99: 0.3 | L99: 0.03 | M99: 0.03 | N99: 0.03 | O99: 0.27 | P99: 0.27 | Q99: 0.27
A100: 2632 | B100: =C100&D100&E100&F100&G100&H100 -> Красота и уходМакияжАксессуары для макияжаПинцеты | C100: Красота и уход | D100: Макияж | E100: Аксессуары для макияжа | F100: Пинцеты | I100: 0.3 | J100: 0.3 | K100: 0.3 | L100: 0.03 | M100: 0.03 | N100: 0.03 | O100: 0.27 | P100: 0.27 | Q100: 0.27
A101: 2633 | B101: =C101&D101&E101&F101&G101&H101 -> Красота и уходМакияжЛицоКушоны | C101: Красота и уход | D101: Макияж | E101: Лицо | F101: Кушоны | I101: 0.2 | J101: 0.2 | K101: 0.2 | L101: 0.02 | M101: 0.02 | N101: 0.02 | O101: 0.18 | P101: 0.18 | Q101: 0.18
...

Sheet Savdo komissiyasi
I2: Chegirmagacha komissiya | L2: Chegirma miqdori (chegirma 19.07.2026-yilgacha amal qiladi) | O2: Chegirmadan keyingi komissiya
A3: category ID | B3: cat_code | C3: category1_ru | D3: category2_ru | E3: category3_ru | F3: category4_ru | G3: category5_ru | H3: category6_ru | I3: comm FBO % | J3: comm FBS % | K3: comm DBS% | L3: Скидка FBO % | M3: Скидка FBS % | N3: Скидка DBS% | O3: comm FBO % | P3: comm FBS % | Q3: comm DBS%
I4: FBO | J4: FBS | K4: DBS | L4: FBO | M4: FBS | N4: DBS | O4: FBO | P4: FBS | Q4: DBS
A5: 11 | B5: =C5&D5&E5&F5&G5&H5 -> Maishiy texnikaKatta maishiy texnikaPechlar | C5: Maishiy texnika | D5: Katta maishiy texnika | E5: Pechlar | I5: 0.1 | J5: 0.1 | K5: 0.1 | L5: 0 | M5: 0 | N5: 0 | O5: 0.1 | P5: 0.1 | Q5: 0.1
A6: 13 | B6: =C6&D6&E6&F6&G6&H6 -> Maishiy texnikaKatta maishiy texnikaPechkalarGaz pechkalar | C6: Maishiy texnika | D6: Katta maishiy texnika | E6: Pechkalar | F6: Gaz pechkalar | I6: 0.1 | J6: 0.1 | K6: 0.1 | L6: 0 | M6: 0 | N6: 0 | O6: 0.1 | P6: 0.1 | Q6: 0.1
A7: 14 | B7: =C7&D7&E7&F7&G7&H7 -> KitoblarDiniy kitoblarXristianlikMuqaddas matnlar | C7: Kitoblar | D7: Diniy kitoblar | E7: Xristianlik | F7: Muqaddas matnlar | I7: 0.2 | J7: 0.2 | K7: 0.2 | L7: 0 | M7: 0 | N7: 0 | O7: 0.2 | P7: 0.2 | Q7: 0.2
A8: 16 | B8: =C8&D8&E8&F8&G8&H8 -> Maishiy texnikaKatta maishiy texnikaQuritgich mashinasi | C8: Maishiy texnika | D8: Katta maishiy texnika | E8: Quritgich mashinasi | I8: 0.1 | J8: 0.1 | K8: 0.1 | L8: 0 | M8: 0 | N8: 0 | O8: 0.1 | P8: 0.1 | Q8: 0.1
A9: 17 | B9: =C9&D9&E9&F9&G9&H9 -> Maishiy texnikaKatta maishiy texnikaIdish yuvish mashinalar | C9: Maishiy texnika | D9: Katta maishiy texnika | E9: Idish yuvish mashinalar | I9: 0.1 | J9: 0.1 | K9: 0.1 | L9: 0 | M9: 0 | N9: 0 | O9: 0.1 | P9: 0.1 | Q9: 0.1
A10: 22 | B10: =C10&D10&E10&F10&G10&H10 -> Qurilish va taʼmirlashUy va bogʻ uchun suv taʼminotiQuvurlarni montaj qilish uchun mahkamlagichQisqichlar va bog'ichlar | C10: Qurilish va taʼmirlash | D10: Uy va bogʻ uchun suv taʼminoti | E10: Quvurlarni montaj qilish uchun mahkamlagich | F10: Qisqichlar va bog'ichlar | I10: 0.2 | J10: 0.2 | K10: 0.2 | L10: 0 | M10: 0 | N10: 0 | O10: 0.2 | P10: 0.2 | Q10: 0.2
A11: 24 | B11: =C11&D11&E11&F11&G11&H11 -> Qurilish va taʼmirlashAsboblarElektr asboblarElektr planerlar | C11: Qurilish va taʼmirlash | D11: Asboblar | E11: Elektr asboblar | F11: Elektr planerlar | I11: 0.15 | J11: 0.15 | K11: 0.15 | L11: 0 | M11: 0 | N11: 0 | O11: 0.15 | P11: 0.15 | Q11: 0.15
A12: 25 | B12: =C12&D12&E12&F12&G12&H12 -> Qurilish va taʼmirlashAsboblarQo'l asboblar to'plami | C12: Qurilish va taʼmirlash | D12: Asboblar | E12: Qo'l asboblar to'plami | I12: 0.15 | J12: 0.15 | K12: 0.15 | L12: 0 | M12: 0 | N12: 0 | O12: 0.15 | P12: 0.15 | Q12: 0.15
A13: 26 | B13: =C13&D13&E13&F13&G13&H13 -> Qurilish va taʼmirlashSantexnikaSantexnika armatura va aksessuarlarРемкомплекты и запчасти | C13: Qurilish va taʼmirlash | D13: Santexnika | E13: Santexnika armatura va aksessuarlar | F13: Ремкомплекты и запчасти | I13: 0.25 | J13: 0.25 | K13: 0.25 | L13: 0 | M13: 0 | N13: 0 | O13: 0.25 | P13: 0.25 | Q13: 0.25
A14: 28 | B14: =C14&D14&E14&F14&G14&H14 -> SalomatlikPrezervativlar, lubrikantlar va prolongatorlarPrezervativlar | C14: Salomatlik | D14: Prezervativlar, lubrikantlar va prolongatorlar | E14: Prezervativlar | I14: 0.25 | J14: 0.25 | K14: 0.25 | L14: 0 | M14: 0 | N14: 0 | O14: 0.25 | P14: 0.25 | Q14: 0.25
A15: 62 | B15: =C15&D15&E15&F15&G15&H15 -> Oziq-ovqat mahsulotlariSuv, sharbatlar, ichimliklarEnergetik ichimliklar | C15: Oziq-ovqat mahsulotlari | D15: Suv, sharbatlar, ichimliklar | E15: Energetik ichimliklar | I15: 0.15 | J15: 0.15 | K15: 0.15 | L15: 0.02 | M15: 0.02 | N15: 0.02 | O15: 0.13 | P15: 0.13 | Q15: 0.13
A16: 63 | B16: =C16&D16&E16&F16&G16&H16 -> MebelOfis va kompyuter mebellariSeyflar | C16: Mebel | D16: Ofis va kompyuter mebellari | E16: Seyflar | I16: 0.15 | J16: 0.15 | K16: 0.15 | L16: 0 | M16: 0 | N16: 0 | O16: 0.15 | P16: 0.15 | Q16: 0.15
A17: 64 | B17: =C17&D17&E17&F17&G17&H17 -> Oziq-ovqat mahsulotlariUn, shakar va tuzTuz | C17: Oziq-ovqat mahsulotlari | D17: Un, shakar va tuz | E17: Tuz | I17: 0.15 | J17: 0.15 | K17: 0.15 | L17: 0.01 | M17: 0.01 | N17: 0.01 | O17: 0.14 | P17: 0.14 | Q17: 0.14
A18: 68 | B18: =C18&D18&E18&F18&G18&H18 -> Kanselyariya tovarlariYozuv qurollariQalam o'tkirlagichlar | C18: Kanselyariya tovarlari | D18: Yozuv qurollari | E18: Qalam o'tkirlagichlar | I18: 0.2 | J18: 0.2 | K18: 0.2 | L18: 0.105 | M18: 0.105 | N18: 0.105 | O18: 0.095 | P18: 0.095 | Q18: 0.095
A19: 69 | B19: =C19&D19&E19&F19&G19&H19 -> Oziq-ovqat mahsulotlariMakaronlar, yormalar va quruq nonushtalarYormalar va dukkaklilarSuli | C19: Oziq-ovqat mahsulotlari | D19: Makaronlar, yormalar va quruq nonushtalar | E19: Yormalar va dukkaklilar | F19: Suli | I19: 0.12 | J19: 0.12 | K19: 0.12 | L19: 0.045 | M19: 0.045 | N19: 0.045 | O19: 0.075 | P19: 0.075 | Q19: 0.075
A20: 70 | B20: =C20&D20&E20&F20&G20&H20 -> Oziq-ovqat mahsulotlariMakaronlar, yormalar va quruq nonushtalarYormalar va dukkaklilarOqlangan tariq | C20: Oziq-ovqat mahsulotlari | D20: Makaronlar, yormalar va quruq nonushtalar | E20: Yormalar va dukkaklilar | F20: Oqlangan tariq | I20: 0.12 | J20: 0.12 | K20: 0.12 | L20: 0.045 | M20: 0.045 | N20: 0.045 | O20: 0.075 | P20: 0.075 | Q20: 0.075
A21: 71 | B21: =C21&D21&E21&F21&G21&H21 -> Oziq-ovqat mahsulotlariSogʻlom ovqatlanishDengiz o'tlari | C21: Oziq-ovqat mahsulotlari | D21: Sogʻlom ovqatlanish | E21: Dengiz o'tlari | I21: 0.15 | J21: 0.15 | K21: 0.15 | L21: 0.01 | M21: 0.01 | N21: 0.01 | O21: 0.14 | P21: 0.14 | Q21: 0.14
A22: 72 | B22: =C22&D22&E22&F22&G22&H22 -> Oziq-ovqat mahsulotlariAsal, murabbo, shirin konservalarSiroplar va toppinglar | C22: Oziq-ovqat mahsulotlari | D22: Asal, murabbo, shirin konservalar | E22: Siroplar va toppinglar | I22: 0.15 | J22: 0.15 | K22: 0.15 | L22: 0.02 | M22: 0.02 | N22: 0.02 | O22: 0.13 | P22: 0.13 | Q22: 0.13
A23: 73 | B23: =C23&D23&E23&F23&G23&H23 -> Oziq-ovqat mahsulotlariMakaronlar, yormalar va quruq nonushtalarYormalar va dukkaklilarPerlovka | C23: Oziq-ovqat mahsulotlari | D23: Makaronlar, yormalar va quruq nonushtalar | E23: Yormalar va dukkaklilar | F23: Perlovka | I23: 0.12 | J23: 0.12 | K23: 0.12 | L23: 0.045 | M23: 0.045 | N23: 0.045 | O23: 0.075 | P23: 0.075 | Q23: 0.075
A24: 77 | B24: =C24&D24&E24&F24&G24&H24 -> AvtotovarlarAvtomobil uchun elektronikaAlkotesterlar | C24: Avtotovarlar | D24: Avtomobil uchun elektronika | E24: Alkotesterlar | I24: 0.2 | J24: 0.2 | K24: 0.2 | L24: 0 | M24: 0 | N24: 0 | O24: 0.2 | P24: 0.2 | Q24: 0.2
A25: 78 | B25: =C25&D25&E25&F25&G25&H25 -> Maishiy texnikaKatta maishiy texnikaPechkalarKombinatsiyalangan pechkalar | C25: Maishiy texnika | D25: Katta maishiy texnika | E25: Pechkalar | F25: Kombinatsiyalangan pechkalar | I25: 0.1 | J25: 0.1 | K25: 0.1 | L25: 0 | M25: 0 | N25: 0 | O25: 0.1 | P25: 0.1 | Q25: 0.1
A26: 81 | B26: =C26&D26&E26&F26&G26&H26 -> Maishiy texnikaKatta maishiy texnikaPechkalarElektr pechkalar | C26: Maishiy texnika | D26: Katta maishiy texnika | E26: Pechkalar | F26: Elektr pechkalar | I26: 0.1 | J26: 0.1 | K26: 0.1 | L26: 0 | M26: 0 | N26: 0 | O26: 0.1 | P26: 0.1 | Q26: 0.1
A27: 82 | B27: =C27&D27&E27&F27&G27&H27 -> Maishiy texnikaKatta maishiy texnikaSovutgichlar va muzlatgichlarSovutgichlar | C27: Maishiy texnika | D27: Katta maishiy texnika | E27: Sovutgichlar va muzlatgichlar | F27: Sovutgichlar | I27: 0.1 | J27: 0.1 | K27: 0.1 | L27: 0 | M27: 0 | N27: 0 | O27: 0.1 | P27: 0.1 | Q27: 0.1
A28: 83 | B28: =C28&D28&E28&F28&G28&H28 -> Maishiy texnikaKatta maishiy texnikaSovutgichlar va muzlatgichlarMuzlatgichlar | C28: Maishiy texnika | D28: Katta maishiy texnika | E28: Sovutgichlar va muzlatgichlar | F28: Muzlatgichlar | I28: 0.1 | J28: 0.1 | K28: 0.1 | L28: 0 | M28: 0 | N28: 0 | O28: 0.1 | P28: 0.1 | Q28: 0.1
A29: 84 | B29: =C29&D29&E29&F29&G29&H29 -> Maishiy texnikaKatta maishiy texnikaSovutgichlar va muzlatgichlarSovutish shkaflari | C29: Maishiy texnika | D29: Katta maishiy texnika | E29: Sovutgichlar va muzlatgichlar | F29: Sovutish shkaflari | I29: 0.1 | J29: 0.1 | K29: 0.1 | L29: 0 | M29: 0 | N29: 0 | O29: 0.1 | P29: 0.1 | Q29: 0.1
A30: 85 | B30: =C30&D30&E30&F30&G30&H30 -> Maishiy texnikaKatta maishiy texnikaSovutgichlar va muzlatgichlarSharob shkaflari | C30: Maishiy texnika | D30: Katta maishiy texnika | E30: Sovutgichlar va muzlatgichlar | F30: Sharob shkaflari | I30: 0.1 | J30: 0.1 | K30: 0.1 | L30: 0 | M30: 0 | N30: 0 | O30: 0.1 | P30: 0.1 | Q30: 0.1
A31: 86 | B31: =C31&D31&E31&F31&G31&H31 -> Xobbi va ijodPazl, mozaika va freskaPazllar | C31: Xobbi va ijod | D31: Pazl, mozaika va freska | E31: Pazllar | I31: 0.22 | J31: 0.22 | K31: 0.22 | L31: 0 | M31: 0 | N31: 0 | O31: 0.22 | P31: 0.22 | Q31: 0.22
A32: 88 | B32: =C32&D32&E32&F32&G32&H32 -> Oziq-ovqat mahsulotlariPishiriq va desertlar uchun mahsulotlarOzuqaviy qoʻshimchalarOzuqaviy bo'yoqlar va aromatizatorlar | C32: Oziq-ovqat mahsulotlari | D32: Pishiriq va desertlar uchun mahsulotlar | E32: Ozuqaviy qoʻshimchalar | F32: Ozuqaviy bo'yoqlar va aromatizatorlar | I32: 0.15 | J32: 0.15 | K32: 0.15 | L32: 0.035 | M32: 0.035 | N32: 0.035 | O32: 0.115 | P32: 0.115 | Q32: 0.115
A33: 90 | B33: =C33&D33&E33&F33&G33&H33 -> Qurilish va taʼmirlashIsitishKengaytiradigan baklar | C33: Qurilish va taʼmirlash | D33: Isitish | E33: Kengaytiradigan baklar | I33: 0.22 | J33: 0.22 | K33: 0.22 | L33: 0 | M33: 0 | N33: 0 | O33: 0.22 | P33: 0.22 | Q33: 0.22
A34: 114 | B34: =C34&D34&E34&F34&G34&H34 -> Oziq-ovqat mahsulotlariSogʻlom ovqatlanishUrbech | C34: Oziq-ovqat mahsulotlari | D34: Sogʻlom ovqatlanish | E34: Urbech | I34: 0.22 | J34: 0.22 | K34: 0.22 | L34: 0 | M34: 0 | N34: 0 | O34: 0.22 | P34: 0.22 | Q34: 0.22
A35: 115 | B35: =C35&D35&E35&F35&G35&H35 -> Oziq-ovqat mahsulotlariAsal, murabbo, shirin konservalarMurabbo, jemlar va yanchilgan rezavorlar | C35: Oziq-ovqat mahsulotlari | D35: Asal, murabbo, shirin konservalar | E35: Murabbo, jemlar va yanchilgan rezavorlar | I35: 0.15 | J35: 0.15 | K35: 0.15 | L35: 0.005 | M35: 0.005 | N35: 0.005 | O35: 0.145 | P35: 0.145 | Q35: 0.145
A36: 125 | B36: =C36&D36&E36&F36&G36&H36 -> Qurilish va taʼmirlashUy va bogʻ uchun suv taʼminotiBerkitish-rostlash armaturasiSharli kranlar | C36: Qurilish va taʼmirlash | D36: Uy va bogʻ uchun suv taʼminoti | E36: Berkitish-rostlash armaturasi | F36: Sharli kranlar | I36: 0.2 | J36: 0.2 | K36: 0.2 | L36: 0 | M36: 0 | N36: 0 | O36: 0.2 | P36: 0.2 | Q36: 0.2
A37: 126 | B37: =C37&D37&E37&F37&G37&H37 -> Qurilish va taʼmirlashIsitishHavo va shlam separatorlari | C37: Qurilish va taʼmirlash | D37: Isitish | E37: Havo va shlam separatorlari | I37: 0.25 | J37: 0.25 | K37: 0.25 | L37: 0 | M37: 0 | N37: 0 | O37: 0.25 | P37: 0.25 | Q37: 0.25
A38: 129 | B38: =C38&D38&E38&F38&G38&H38 -> Qurilish va taʼmirlashIsitishIssiq pollarSuvda isitiladigan polIssiq pollar uchun harorat | C38: Qurilish va taʼmirlash | D38: Isitish | E38: Issiq pollar | F38: Suvda isitiladigan pol | G38: Issiq pollar uchun harorat | I38: 0.25 | J38: 0.25 | K38: 0.25 | L38: 0 | M38: 0 | N38: 0 | O38: 0.25 | P38: 0.25 | Q38: 0.25
A39: 130 | B39: =C39&D39&E39&F39&G39&H39 -> Qurilish va taʼmirlashIsitishIssiq pollarSuvda isitiladigan polKollektor guruhlari | C39: Qurilish va taʼmirlash | D39: Isitish | E39: Issiq pollar | F39: Suvda isitiladigan pol | G39: Kollektor guruhlari | I39: 0.25 | J39: 0.25 | K39: 0.25 | L39: 0 | M39: 0 | N39: 0 | O39: 0.25 | P39: 0.25 | Q39: 0.25
A40: 132 | B40: =C40&D40&E40&F40&G40&H40 -> Oziq-ovqat mahsulotlariKonservalarKonservalangan ovqatlar | C40: Oziq-ovqat mahsulotlari | D40: Konservalar | E40: Konservalangan ovqatlar | I40: 0.15 | J40: 0.15 | K40: 0.15 | L40: 0 | M40: 0 | N40: 0 | O40: 0.15 | P40: 0.15 | Q40: 0.15
A41: 134 | B41: =C41&D41&E41&F41&G41&H41 -> Oziq-ovqat mahsulotlariYog'lar, souslar va ziravorlarZiravorlar | C41: Oziq-ovqat mahsulotlari | D41: Yog'lar, souslar va ziravorlar | E41: Ziravorlar | I41: 0.15 | J41: 0.15 | K41: 0.15 | L41: 0.01 | M41: 0.01 | N41: 0.01 | O41: 0.14 | P41: 0.14 | Q41: 0.14
A42: 135 | B42: =C42&D42&E42&F42&G42&H42 -> Oziq-ovqat mahsulotlariUn, shakar va tuzShakar | C42: Oziq-ovqat mahsulotlari | D42: Un, shakar va tuz | E42: Shakar | I42: 0.05 | J42: 0.05 | K42: 0.05 | L42: 0.01 | M42: 0.01 | N42: 0.01 | O42: 0.04 | P42: 0.04 | Q42: 0.04
A43: 136 | B43: =C43&D43&E43&F43&G43&H43 -> Oziq-ovqat mahsulotlariUn, shakar va tuzUn | C43: Oziq-ovqat mahsulotlari | D43: Un, shakar va tuz | E43: Un | I43: 0.15 | J43: 0.15 | K43: 0.15 | L43: 0.01 | M43: 0.01 | N43: 0.01 | O43: 0.14 | P43: 0.14 | Q43: 0.14
A44: 138 | B44: =C44&D44&E44&F44&G44&H44 -> Oziq-ovqat mahsulotlariYog'lar, souslar va ziravorlarSouslarSirka | C44: Oziq-ovqat mahsulotlari | D44: Yog'lar, souslar va ziravorlar | E44: Souslar | F44: Sirka | I44: 0.15 | J44: 0.15 | K44: 0.15 | L44: 0.01 | M44: 0.01 | N44: 0.01 | O44: 0.14 | P44: 0.14 | Q44: 0.14
A45: 142 | B45: =C45&D45&E45&F45&G45&H45 -> Oziq-ovqat mahsulotlariMakaronlar, yormalar va quruq nonushtalarMakaronlar | C45: Oziq-ovqat mahsulotlari | D45: Makaronlar, yormalar va quruq nonushtalar | E45: Makaronlar | I45: 0.12 | J45: 0.12 | K45: 0.12 | L45: 0.045 | M45: 0.045 | N45: 0.045 | O45: 0.075 | P45: 0.075 | Q45: 0.075
A46: 143 | B46: =C46&D46&E46&F46&G46&H46 -> Oziq-ovqat mahsulotlariChoy, qahva va kakaoQoʻshimchalar qoʻshilgan choy | C46: Oziq-ovqat mahsulotlari | D46: Choy, qahva va kakao | E46: Qoʻshimchalar qoʻshilgan choy | I46: 0.17 | J46: 0.17 | K46: 0.17 | L46: 0.01 | M46: 0.01 | N46: 0.01 | O46: 0.16 | P46: 0.16 | Q46: 0.16
A47: 326 | B47: =C47&D47&E47&F47&G47&H47 -> Oziq-ovqat mahsulotlariSneklar, yong'oqlar va pistalarYongʻoqlar | C47: Oziq-ovqat mahsulotlari | D47: Sneklar, yong'oqlar va pistalar | E47: Yongʻoqlar | I47: 0.15 | J47: 0.15 | K47: 0.15 | L47: 0.01 | M47: 0.01 | N47: 0.01 | O47: 0.14 | P47: 0.14 | Q47: 0.14
A48: 329 | B48: =C48&D48&E48&F48&G48&H48 -> Oziq-ovqat mahsulotlariSogʻlom ovqatlanishBalzamlar, toniklar, eliksirlar | C48: Oziq-ovqat mahsulotlari | D48: Sogʻlom ovqatlanish | E48: Balzamlar, toniklar, eliksirlar | I48: 0.15 | J48: 0.15 | K48: 0.15 | L48: 0.01 | M48: 0.01 | N48: 0.01 | O48: 0.14 | P48: 0.14 | Q48: 0.14
A49: 356 | B49: =C49&D49&E49&F49&G49&H49 -> Oziq-ovqat mahsulotlariPishirish va shirinliklarShokolad | C49: Oziq-ovqat mahsulotlari | D49: Pishirish va shirinliklar | E49: Shokolad | I49: 0.2 | J49: -% | K49: 0.2 | L49: 0.015 | M49: 0.015 | N49: 0.015 | O49: 0.185 | P49: -% | Q49: 0.185
A50: 366 | B50: =C50&D50&E50&F50&G50&H50 -> Oziq-ovqat mahsulotlariSogʻlom ovqatlanishQarsildoq nonlar | C50: Oziq-ovqat mahsulotlari | D50: Sogʻlom ovqatlanish | E50: Qarsildoq nonlar | I50: 0.15 | J50: 0.15 | K50: 0.15 | L50: 0 | M50: 0 | N50: 0 | O50: 0.15 | P50: 0.15 | Q50: 0.15
A51: 369 | B51: =C51&D51&E51&F51&G51&H51 -> Oziq-ovqat mahsulotlariPishirish va shirinliklarBatonchalar | C51: Oziq-ovqat mahsulotlari | D51: Pishirish va shirinliklar | E51: Batonchalar | I51: 0.2 | J51: -% | K51: 0.2 | L51: 0.015 | M51: 0.015 | N51: 0.015 | O51: 0.185 | P51: -% | Q51: 0.185
A52: 531 | B52: =C52&D52&E52&F52&G52&H52 -> Oziq-ovqat mahsulotlariKonservalarKonservalangan goʻsht | C52: Oziq-ovqat mahsulotlari | D52: Konservalar | E52: Konservalangan goʻsht | I52: 0.15 | J52: 0.15 | K52: 0.15 | L52: 0.005 | M52: 0.005 | N52: 0.005 | O52: 0.145 | P52: 0.145 | Q52: 0.145
A53: 555 | B53: =C53&D53&E53&F53&G53&H53 -> Oziq-ovqat mahsulotlariChoy, qahva va kakaoSikoriy | C53: Oziq-ovqat mahsulotlari | D53: Choy, qahva va kakao | E53: Sikoriy | I53: 0.17 | J53: 0.17 | K53: 0.17 | L53: 0 | M53: 0 | N53: 0 | O53: 0.17 | P53: 0.17 | Q53: 0.17
A54: 1892 | B54: =C54&D54&E54&F54&G54&H54 -> Oziq-ovqat mahsulotlariPishirish va shirinliklarSaqichlar | C54: Oziq-ovqat mahsulotlari | D54: Pishirish va shirinliklar | E54: Saqichlar | I54: 0.2 | J54: 0.2 | K54: 0.2 | L54: 0.015 | M54: 0.015 | N54: 0.015 | O54: 0.185 | P54: 0.185 | Q54: 0.185
A55: 1915 | B55: =C55&D55&E55&F55&G55&H55 -> Oziq-ovqat mahsulotlariPishirish va shirinliklarShokoladli, yongʻoqli pasta | C55: Oziq-ovqat mahsulotlari | D55: Pishirish va shirinliklar | E55: Shokoladli, yongʻoqli pasta | I55: 0.2 | J55: 0.2 | K55: 0.2 | L55: 0.015 | M55: 0.015 | N55: 0.015 | O55: 0.185 | P55: 0.185 | Q55: 0.185
A56: 2477 | B56: =C56&D56&E56&F56&G56&H56 -> Oziq-ovqat mahsulotlariKonservalarKonservalangan sabzavotlar | C56: Oziq-ovqat mahsulotlari | D56: Konservalar | E56: Konservalangan sabzavotlar | I56: 0.15 | J56: 0.15 | K56: 0.15 | L56: 0.005 | M56: 0.005 | N56: 0.005 | O56: 0.145 | P56: 0.145 | Q56: 0.145
A57: 2481 | B57: =C57&D57&E57&F57&G57&H57 -> Oziq-ovqat mahsulotlariSneklar, yong'oqlar va pistalarQurt | C57: Oziq-ovqat mahsulotlari | D57: Sneklar, yong'oqlar va pistalar | E57: Qurt | I57: 0.22 | J57: 0.22 | K57: 0.22 | L57: 0.01 | M57: 0.01 | N57: 0.01 | O57: 0.21 | P57: 0.21 | Q57: 0.21
A58: 2570 | B58: =C58&D58&E58&F58&G58&H58 -> Goʻzallik va parvarishShaxsiy gigiyenaPaxta mahsulotlariNam salfetkalar | C58: Goʻzallik va parvarish | D58: Shaxsiy gigiyena | E58: Paxta mahsulotlari | F58: Nam salfetkalar | I58: 0.2 | J58: 0.2 | K58: 0.2 | L58: 0.02 | M58: 0.02 | N58: 0.02 | O58: 0.18 | P58: 0.18 | Q58: 0.18
A59: 2571 | B59: =C59&D59&E59&F59&G59&H59 -> Goʻzallik va parvarishShaxsiy gigiyenaOgʻiz boʻshligʻi gigiyenasiTish ipi | C59: Goʻzallik va parvarish | D59: Shaxsiy gigiyena | E59: Ogʻiz boʻshligʻi gigiyenasi | F59: Tish ipi | I59: 0.2 | J59: 0.2 | K59: 0.2 | L59: 0.02 | M59: 0.02 | N59: 0.02 | O59: 0.18 | P59: 0.18 | Q59: 0.18
A60: 2572 | B60: =C60&D60&E60&F60&G60&H60 -> Goʻzallik va parvarishShaxsiy gigiyenaOgʻiz boʻshligʻi gigiyenasiElektr tish choʻtkalari | C60: Goʻzallik va parvarish | D60: Shaxsiy gigiyena | E60: Ogʻiz boʻshligʻi gigiyenasi | F60: Elektr tish choʻtkalari | I60: 0.2 | J60: 0.2 | K60: 0.2 | L60: 0.01 | M60: 0.01 | N60: 0.01 | O60: 0.19 | P60: 0.19 | Q60: 0.19
A61: 2573 | B61: =C61&D61&E61&F61&G61&H61 -> Goʻzallik va parvarishShaxsiy gigiyenaOgʻiz boʻshligʻi gigiyenasiElektr tish choʻtkalari va irrigatorlar uchun nasadkalar | C61: Goʻzallik va parvarish | D61: Shaxsiy gigiyena | E61: Ogʻiz boʻshligʻi gigiyenasi | F61: Elektr tish choʻtkalari va irrigatorlar uchun nasadkalar | I61: 0.2 | J61: 0.2 | K61: 0.2 | L61: 0.01 | M61: 0.01 | N61: 0.01 | O61: 0.19 | P61: 0.19 | Q61: 0.19
A62: 2574 | B62: =C62&D62&E62&F62&G62&H62 -> Goʻzallik va parvarishShaxsiy gigiyenaOgʻiz boʻshligʻi gigiyenasiElektr tish choʻtkalari va irrigatorlar uchun aksessuarlar | C62: Goʻzallik va parvarish | D62: Shaxsiy gigiyena | E62: Ogʻiz boʻshligʻi gigiyenasi | F62: Elektr tish choʻtkalari va irrigatorlar uchun aksessuarlar | I62: 0.2 | J62: 0.2 | K62: 0.2 | L62: 0.01 | M62: 0.01 | N62: 0.01 | O62: 0.19 | P62: 0.19 | Q62: 0.19
A63: 2575 | B63: =C63&D63&E63&F63&G63&H63 -> Bolalar tovarlariAravachalar va avtomobil uchun oʻrindiqlarAravachalar va avtomobil o'rindiqlari uchun aksessuarlar | C63: Bolalar tovarlari | D63: Aravachalar va avtomobil uchun oʻrindiqlar | E63: Aravachalar va avtomobil o'rindiqlari uchun aksessuarlar | I63: 0.25 | J63: 0.25 | K63: 0.25 | L63: 0 | M63: 0 | N63: 0 | O63: 0.25 | P63: 0.25 | Q63: 0.25
A64: 2576 | B64: =C64&D64&E64&F64&G64&H64 -> Bolalar tovarlariOʻyinchoqlar va oʻyinlarChoʻmilish uchun oʻyinchoqlar | C64: Bolalar tovarlari | D64: Oʻyinchoqlar va oʻyinlar | E64: Choʻmilish uchun oʻyinchoqlar | I64: 0.3 | J64: 0.3 | K64: 0.3 | L64: 0 | M64: 0 | N64: 0 | O64: 0.3 | P64: 0.3 | Q64: 0.3
A65: 2577 | B65: =C65&D65&E65&F65&G65&H65 -> Bolalar tovarlariOvqatlantirish uchun tovarlarOvqatlantirish uchun idishlar va anjomlariBolalar uchun likopchalar va miskalar | C65: Bolalar tovarlari | D65: Ovqatlantirish uchun tovarlar | E65: Ovqatlantirish uchun idishlar va anjomlari | F65: Bolalar uchun likopchalar va miskalar | I65: 0.2 | J65: 0.2 | K65: 0.2 | L65: 0.015 | M65: 0.015 | N65: 0.015 | O65: 0.185 | P65: 0.185 | Q65: 0.185
A66: 2578 | B66: =C66&D66&E66&F66&G66&H66 -> Bolalar tovarlariGigiyena va tagliklarOgʻiz boʻshligʻi gigiyenasiBolalar tish pastalari | C66: Bolalar tovarlari | D66: Gigiyena va tagliklar | E66: Ogʻiz boʻshligʻi gigiyenasi | F66: Bolalar tish pastalari | I66: 0.2 | J66: 0.2 | K66: 0.2 | L66: 0 | M66: 0 | N66: 0 | O66: 0.2 | P66: 0.2 | Q66: 0.2
A67: 2580 | B67: =C67&D67&E67&F67&G67&H67 -> Bolalar tovarlariOʻyinchoqlar va oʻyinlarKonstruktorlarYogʻochdan | C67: Bolalar tovarlari | D67: Oʻyinchoqlar va oʻyinlar | E67: Konstruktorlar | F67: Yogʻochdan | I67: 0.2 | J67: 0.2 | K67: 0.2 | L67: 0.03 | M67: 0.03 | N67: 0.03 | O67: 0.17 | P67: 0.17 | Q67: 0.17
A68: 2581 | B68: =C68&D68&E68&F68&G68&H68 -> Bolalar tovarlariOʻyinchoqlar va oʻyinlarKonstruktorlarMagnitli | C68: Bolalar tovarlari | D68: Oʻyinchoqlar va oʻyinlar | E68: Konstruktorlar | F68: Magnitli | I68: 0.2 | J68: 0.2 | K68: 0.2 | L68: 0.03 | M68: 0.03 | N68: 0.03 | O68: 0.17 | P68: 0.17 | Q68: 0.17
A69: 2582 | B69: =C69&D69&E69&F69&G69&H69 -> Bolalar tovarlariOʻyinchoqlar va oʻyinlarKonstruktorlarBloklar | C69: Bolalar tovarlari | D69: Oʻyinchoqlar va oʻyinlar | E69: Konstruktorlar | F69: Bloklar | I69: 0.2 | J69: 0.2 | K69: 0.2 | L69: 0 | M69: 0 | N69: 0 | O69: 0.2 | P69: 0.2 | Q69: 0.2
A70: 2583 | B70: =C70&D70&E70&F70&G70&H70 -> Bolalar tovarlariOʻyinchoqlar va oʻyinlarKonstruktorlarMetalldan | C70: Bolalar tovarlari | D70: Oʻyinchoqlar va oʻyinlar | E70: Konstruktorlar | F70: Metalldan | I70: 0.2 | J70: 0.2 | K70: 0.2 | L70: 0.03 | M70: 0.03 | N70: 0.03 | O70: 0.17 | P70: 0.17 | Q70: 0.17
A71: 2584 | B71: =C71&D71&E71&F71&G71&H71 -> Bolalar tovarlariOʻyinchoqlar va oʻyinlarYogʻoch oʻyinchoqlar | C71: Bolalar tovarlari | D71: Oʻyinchoqlar va oʻyinlar | E71: Yogʻoch oʻyinchoqlar | I71: 0.2 | J71: 0.2 | K71: 0.2 | L71: 0.02 | M71: 0.02 | N71: 0.02 | O71: 0.18 | P71: 0.18 | Q71: 0.18
A72: 2585 | B72: =C72&D72&E72&F72&G72&H72 -> Bolalar tovarlariOʻyinchoqlar va oʻyinlarQoʻgʻirchoqlar uychalari | C72: Bolalar tovarlari | D72: Oʻyinchoqlar va oʻyinlar | E72: Qoʻgʻirchoqlar uychalari | I72: 0.2 | J72: 0.2 | K72: 0.2 | L72: 0.03 | M72: 0.03 | N72: 0.03 | O72: 0.17 | P72: 0.17 | Q72: 0.17
A73: 2586 | B73: =C73&D73&E73&F73&G73&H73 -> Bolalar tovarlariOʻyinchoqlar va oʻyinlarOʻyinchoqlar – antistress | C73: Bolalar tovarlari | D73: Oʻyinchoqlar va oʻyinlar | E73: Oʻyinchoqlar – antistress | I73: 0.2 | J73: 0.2 | K73: 0.2 | L73: 0 | M73: 0 | N73: 0 | O73: 0.2 | P73: 0.2 | Q73: 0.2
A74: 2587 | B74: =C74&D74&E74&F74&G74&H74 -> Bolalar tovarlariOʻyinchoqlar va oʻyinlarFigurachalar va aksessuarlar | C74: Bolalar tovarlari | D74: Oʻyinchoqlar va oʻyinlar | E74: Figurachalar va aksessuarlar | I74: 0.2 | J74: 0.2 | K74: 0.2 | L74: 0.03 | M74: 0.03 | N74: 0.03 | O74: 0.17 | P74: 0.17 | Q74: 0.17
A75: 2588 | B75: =C75&D75&E75&F75&G75&H75 -> Bolalar tovarlariOʻyinchoqlar va oʻyinlarOʻrgatuvchi va rivojlantiruvchi oʻyinchoqlarSyujetli-rolli oʻyinlar | C75: Bolalar tovarlari | D75: Oʻyinchoqlar va oʻyinlar | E75: Oʻrgatuvchi va rivojlantiruvchi oʻyinchoqlar | F75: Syujetli-rolli oʻyinlar | I75: 0.2 | J75: 0.2 | K75: 0.2 | L75: 0 | M75: 0 | N75: 0 | O75: 0.2 | P75: 0.2 | Q75: 0.2
A76: 2590 | B76: =C76&D76&E76&F76&G76&H76 -> Sport va hordiqSuv sporti va suvda dam olishSuzishDoiralar va matraslarSuzish uchun matraslar | C76: Sport va hordiq | D76: Suv sporti va suvda dam olish | E76: Suzish | F76: Doiralar va matraslar | G76: Suzish uchun matraslar | I76: 0.25 | J76: 0.25 | K76: 0.25 | L76: 0.01 | M76: 0.01 | N76: 0.01 | O76: 0.24 | P76: 0.24 | Q76: 0.24
A77: 2592 | B77: =C77&D77&E77&F77&G77&H77 -> Bolalar tovarlariBolalar sporti va faol hordiqOchiq havoda oʻynaladigan oʻyinlarVarraklar | C77: Bolalar tovarlari | D77: Bolalar sporti va faol hordiq | E77: Ochiq havoda oʻynaladigan oʻyinlar | F77: Varraklar | I77: 0.25 | J77: 0.25 | K77: 0.25 | L77: 0.02 | M77: 0.02 | N77: 0.02 | O77: 0.23 | P77: 0.23 | Q77: 0.23
A78: 2593 | B78: =C78&D78&E78&F78&G78&H78 -> Bolalar tovarlariBolalar sporti va faol hordiqOchiq havoda oʻynaladigan oʻyinlarBumeranglar | C78: Bolalar tovarlari | D78: Bolalar sporti va faol hordiq | E78: Ochiq havoda oʻynaladigan oʻyinlar | F78: Bumeranglar | I78: 0.25 | J78: 0.25 | K78: 0.25 | L78: 0 | M78: 0 | N78: 0 | O78: 0.25 | P78: 0.25 | Q78: 0.25
A79: 2594 | B79: =C79&D79&E79&F79&G79&H79 -> Bolalar tovarlariBolalar sporti va faol hordiqOchiq havoda oʻynaladigan oʻyinlarFrisbi | C79: Bolalar tovarlari | D79: Bolalar sporti va faol hordiq | E79: Ochiq havoda oʻynaladigan oʻyinlar | F79: Frisbi | I79: 0.25 | J79: 0.25 | K79: 0.25 | L79: 0.02 | M79: 0.02 | N79: 0.02 | O79: 0.23 | P79: 0.23 | Q79: 0.23
A80: 2595 | B80: =C80&D80&E80&F80&G80&H80 -> Bolalar tovarlariBolalar sporti va faol hordiqOchiq havoda oʻynaladigan oʻyinlarSport oʻyinlari | C80: Bolalar tovarlari | D80: Bolalar sporti va faol hordiq | E80: Ochiq havoda oʻynaladigan oʻyinlar | F80: Sport oʻyinlari | I80: 0.2 | J80: 0.2 | K80: 0.2 | L80: 0 | M80: 0 | N80: 0 | O80: 0.2 | P80: 0.2 | Q80: 0.2
A81: 2597 | B81: =C81&D81&E81&F81&G81&H81 -> Bolalar tovarlariOʻyinchoqlar va oʻyinlarOʻrgatuvchi va rivojlantiruvchi oʻyinchoqlarO'quv o'yinchoqlar va o'yinlar | C81: Bolalar tovarlari | D81: Oʻyinchoqlar va oʻyinlar | E81: Oʻrgatuvchi va rivojlantiruvchi oʻyinchoqlar | F81: O'quv o'yinchoqlar va o'yinlar | I81: 0.2 | J81: 0.2 | K81: 0.2 | L81: 0.03 | M81: 0.03 | N81: 0.03 | O81: 0.17 | P81: 0.17 | Q81: 0.17
A82: 2598 | B82: =C82&D82&E82&F82&G82&H82 -> Qurilish va taʼmirlashEshiklar, derazalar va butlovchi qismlarRolstavnlar | C82: Qurilish va taʼmirlash | D82: Eshiklar, derazalar va butlovchi qismlar | E82: Rolstavnlar | I82: -% | J82: -% | K82: 0.1 | L82: -% | M82: -% | N82: 0 | O82: -% | P82: -% | Q82: 0.1
A83: 2599 | B83: =C83&D83&E83&F83&G83&H83 -> KiyimAyollar kiyimiChoʻmilish va plyaj kiyimlariIkki qismli choʻmilish kiyimlari | C83: Kiyim | D83: Ayollar kiyimi | E83: Choʻmilish va plyaj kiyimlari | F83: Ikki qismli choʻmilish kiyimlari | I83: 0.25 | J83: 0.25 | K83: 0.25 | L83: 0 | M83: 0 | N83: 0 | O83: 0.25 | P83: 0.25 | Q83: 0.25
A84: 2600 | B84: =C84&D84&E84&F84&G84&H84 -> KiyimAyollar kiyimiChoʻmilish va plyaj kiyimlariPlaj liboslari va tunikalar | C84: Kiyim | D84: Ayollar kiyimi | E84: Choʻmilish va plyaj kiyimlari | F84: Plaj liboslari va tunikalar | I84: 0.25 | J84: 0.25 | K84: 0.25 | L84: 0 | M84: 0 | N84: 0 | O84: 0.25 | P84: 0.25 | Q84: 0.25
A85: 2601 | B85: =C85&D85&E85&F85&G85&H85 -> KiyimAyollar kiyimiIchki kiyimMaykalar va ichki kiyimli toplar | C85: Kiyim | D85: Ayollar kiyimi | E85: Ichki kiyim | F85: Maykalar va ichki kiyimli toplar | I85: 0.25 | J85: 0.25 | K85: 0.25 | L85: 0 | M85: 0 | N85: 0 | O85: 0.25 | P85: 0.25 | Q85: 0.25
A86: 2603 | B86: =C86&D86&E86&F86&G86&H86 -> KiyimErkaklar kiyimiUy kiyimiUy uchun kombinezonlar | C86: Kiyim | D86: Erkaklar kiyimi | E86: Uy kiyimi | F86: Uy uchun kombinezonlar | I86: 0.25 | J86: 0.25 | K86: 0.25 | L86: 0 | M86: 0 | N86: 0 | O86: 0.25 | P86: 0.25 | Q86: 0.25
A87: 2605 | B87: =C87&D87&E87&F87&G87&H87 -> KiyimOʻgʻil bolalar uchun kiyimlarPaypoqlarKolgotkilar | C87: Kiyim | D87: Oʻgʻil bolalar uchun kiyimlar | E87: Paypoqlar | F87: Kolgotkilar | I87: 0.25 | J87: 0.25 | K87: 0.25 | L87: 0 | M87: 0 | N87: 0 | O87: 0.25 | P87: 0.25 | Q87: 0.25
A88: 2607 | B88: =C88&D88&E88&F88&G88&H88 -> AksessuarlarAyollar aksessuarlariSoatlar va qayishlarSoat | C88: Aksessuarlar | D88: Ayollar aksessuarlari | E88: Soatlar va qayishlar | F88: Soat | I88: 0.25 | J88: 0.25 | K88: 0.25 | L88: 0 | M88: 0 | N88: 0 | O88: 0.25 | P88: 0.25 | Q88: 0.25
A89: 2608 | B89: =C89&D89&E89&F89&G89&H89 -> AksessuarlarAyollar aksessuarlariSoatlar va qayishlarSoatlar uchun qayishlar | C89: Aksessuarlar | D89: Ayollar aksessuarlari | E89: Soatlar va qayishlar | F89: Soatlar uchun qayishlar | I89: 0.3 | J89: 0.3 | K89: 0.3 | L89: 0 | M89: 0 | N89: 0 | O89: 0.3 | P89: 0.3 | Q89: 0.3
A90: 2610 | B90: =C90&D90&E90&F90&G90&H90 -> AksessuarlarErkaklar aksessuarlariSoatlar va qayishlarSoat | C90: Aksessuarlar | D90: Erkaklar aksessuarlari | E90: Soatlar va qayishlar | F90: Soat | I90: 0.25 | J90: 0.25 | K90: 0.25 | L90: 0 | M90: 0 | N90: 0 | O90: 0.25 | P90: 0.25 | Q90: 0.25
A91: 2611 | B91: =C91&D91&E91&F91&G91&H91 -> Qurilish va taʼmirlashMateriallar va jihozlarUskunalarJihozlarAsboblar uchun materiallar | C91: Qurilish va taʼmirlash | D91: Materiallar va jihozlar | E91: Uskunalar | F91: Jihozlar | G91: Asboblar uchun materiallar | I91: 0.22 | J91: 0.22 | K91: 0.22 | L91: 0 | M91: 0 | N91: 0 | O91: 0.22 | P91: 0.22 | Q91: 0.22
A92: 2614 | B92: =C92&D92&E92&F92&G92&H92 -> Kanselyariya tovarlariMaktab va oʻqish uchun tovarlarPenallar | C92: Kanselyariya tovarlari | D92: Maktab va oʻqish uchun tovarlar | E92: Penallar | I92: 0.2 | J92: 0.2 | K92: 0.2 | L92: 0 | M92: 0 | N92: 0 | O92: 0.2 | P92: 0.2 | Q92: 0.2
A93: 2615 | B93: =C93&D93&E93&F93&G93&H93 -> AvtotovarlarAksessuarlar va jihozlarBoshqa avtomobil aksessuarlari | C93: Avtotovarlar | D93: Aksessuarlar va jihozlar | E93: Boshqa avtomobil aksessuarlari | I93: 0.25 | J93: 0.25 | K93: 0.25 | L93: 0 | M93: 0 | N93: 0 | O93: 0.25 | P93: 0.25 | Q93: 0.25
A94: 2622 | B94: =C94&D94&E94&F94&G94&H94 -> Qurilish va taʼmirlashYoritishChiroqi musiqa | C94: Qurilish va taʼmirlash | D94: Yoritish | E94: Chiroqi musiqa | I94: 0.22 | J94: 0.22 | K94: 0.22 | L94: 0 | M94: 0 | N94: 0 | O94: 0.22 | P94: 0.22 | Q94: 0.22
A95: 2625 | B95: =C95&D95&E95&F95&G95&H95 -> Turizm, baliq ovi va ovchilikTurizm va ochiq havoda dam olishTurizm va dam olish uchun aksessuarlar | C95: Turizm, baliq ovi va ovchilik | D95: Turizm va ochiq havoda dam olish | E95: Turizm va dam olish uchun aksessuarlar | I95: 0.25 | J95: 0.25 | K95: 0.25 | L95: 0 | M95: 0 | N95: 0 | O95: 0.25 | P95: 0.25 | Q95: 0.25
A96: 2627 | B96: =C96&D96&E96&F96&G96&H96 -> Turizm, baliq ovi va ovchilikTurizm va ochiq havoda dam olishOsma qozonchalar va gulhan uchun uch oyoq | C96: Turizm, baliq ovi va ovchilik | D96: Turizm va ochiq havoda dam olish | E96: Osma qozonchalar va gulhan uchun uch oyoq | I96: 0.25 | J96: 0.25 | K96: 0.25 | L96: 0 | M96: 0 | N96: 0 | O96: 0.25 | P96: 0.25 | Q96: 0.25
A97: 2628 | B97: =C97&D97&E97&F97&G97&H97 -> Turizm, baliq ovi va ovchilikTurizm va ochiq havoda dam olishSayohat uchun idishlar | C97: Turizm, baliq ovi va ovchilik | D97: Turizm va ochiq havoda dam olish | E97: Sayohat uchun idishlar | I97: 0.25 | J97: 0.25 | K97: 0.25 | L97: 0 | M97: 0 | N97: 0 | O97: 0.25 | P97: 0.25 | Q97: 0.25
A98: 2629 | B98: =C98&D98&E98&F98&G98&H98 -> Turizm, baliq ovi va ovchilikTurizm va ochiq havoda dam olishSuvdonlar va ichimlik tizimlariSuvdonlar | C98: Turizm, baliq ovi va ovchilik | D98: Turizm va ochiq havoda dam olish | E98: Suvdonlar va ichimlik tizimlari | F98: Suvdonlar | I98: 0.25 | J98: 0.25 | K98: 0.25 | L98: 0 | M98: 0 | N98: 0 | O98: 0.25 | P98: 0.25 | Q98: 0.25
A99: 2631 | B99: =C99&D99&E99&F99&G99&H99 -> Goʻzallik va parvarishMakiyajMakiyaj uchun aksessuarlarSponj va aplikatorlar | C99: Goʻzallik va parvarish | D99: Makiyaj | E99: Makiyaj uchun aksessuarlar | F99: Sponj va aplikatorlar | I99: 0.3 | J99: 0.3 | K99: 0.3 | L99: 0.03 | M99: 0.03 | N99: 0.03 | O99: 0.27 | P99: 0.27 | Q99: 0.27
A100: 2632 | B100: =C100&D100&E100&F100&G100&H100 -> Goʻzallik va parvarishMakiyajMakiyaj uchun aksessuarlarPinsetlar | C100: Goʻzallik va parvarish | D100: Makiyaj | E100: Makiyaj uchun aksessuarlar | F100: Pinsetlar | I100: 0.3 | J100: 0.3 | K100: 0.3 | L100: 0.03 | M100: 0.03 | N100: 0.03 | O100: 0.27 | P100: 0.27 | Q100: 0.27
A101: 2633 | B101: =C101&D101&E101&F101&G101&H101 -> Goʻzallik va parvarishMakiyajYuzKushonlar | C101: Goʻzallik va parvarish | D101: Makiyaj | E101: Yuz | F101: Kushonlar | I101: 0.2 | J101: 0.2 | K101: 0.2 | L101: 0.02 | M101: 0.02 | N101: 0.02 | O101: 0.18 | P101: 0.18 | Q101: 0.18
...

Sheet Тариф на логистику (логсбор)
A1: Новый тариф на логистику (лог.сбор)
A3: 5250 | B3: сум | C3: до 1 литра* включительно
A4: 250 | B4: сум | C4: за каждый дополнительный литр* (сверх 1го литра)
A6: 50000 | B6: сум | C6: максимальный тариф
A7: 50000 | B7: сум | C7: за доставку товара без ВГХ**
A9: * объем (литраж) округляется вверх до целого
A10: например:
A11: 1,6 литров -> 2 литра
A12: 5,2 литра -> 6 литров
A13: 104,3 литра -> 105 литров
A14: объем в литрах = длина (мм)* ширина (мм) * высота (мм) / 1000000
A15: ** нет данных о длине/ширине/высоте

Sheet Logistika tarifi (log-yig‘im)
A1: Logistika uchun yangi tarif (log-yig‘im)
A3: 5250 | B3: so‘m | C3: 1 litrgacha* shu jumladan
A4: 250 | B4: so‘m | C4: har bir qo‘shimcha litr* uchun (1 litrdan ortiq)
A6: 50000 | B6: so‘m | C6: maksimal tarif
A7: 50000 | B7: so‘m | C7: tovarni VGXsiz yetkazib berganlik uchun**
A9: * hajm (litr) butun songacha yaxlitlanadi
A10: masalan:
A11: 1,6 litr -> 2 litr
A12: 5,2 litr -> 6 litr
A13: 104,3 litr -> 105 litr
A14: *** litrdagi hajm = uzunlik (mm) * eni (mm) * balandlik (mm) / 1000000
A15: ** uzunlik/kenglik/balandlik haqida ma’lumot yo‘q

Sheet Тариф на хранение
A1: Новый тариф на хранение
A3: Стандарный тариф
A4: Оборачиваемость | B4: Тариф
A5: 0–60 дней | B5: бесплатно | D5: 0 | E5: 0
A6: 61–180 дней | B6: 12 сум за каждый литр* в день | D6: 12 | E6: 61
A7: 181–360 дней | B7: 18 сум за каждый литр в день | D7: 18 | E7: 181
A8: 361 и более дней** | B8: 24 сум за каждый литр в день | D8: 24 | E8: 361
A10: максимальный тариф | B10: 5000 сум за каждый товар в день | D10: 5000
A12: Тариф для категорий со специальными тарифами (см Лист Приложение 1)
A13: Оборачиваемость | B13: Тариф
A14: 0–60 дней | B14: бесплатно | D14: 0 | E14: 0
A15: 61–180 дней | B15: 12 сум за каждый литр в день | D15: 12 | E15: 61
A16: 181–360 дней | B16: 14 сум за каждый литр в день | D16: 14 | E16: 181
A17: 361 и более дней** | B17: 18 сум за каждый литр в день | D17: 18 | E17: 361
A19: максимальный тариф | B19: 3000 сум за каждый товар в день | D19: 3000
A21: Бесплатное хранение нового стока
A22: от 30 до 60 дней (см Лист Приложение 2)
A24: * объем (литраж) округляется вверх до целого
A25: например:
A26: 1,6 литров -> 2 литра
A27: 5,2 литра -> 6 литров
A28: 104,3 литра -> 105 литров
A29: объем в литрах = длина (мм)* ширина (мм) * высота (мм) / 1000000
A30: ** в том числе без продаж за период расчета оборачиваемости

Sheet Saqlash uchun tarif
A1: Yangi saqlash tarifi
A3: Standart tarif
A4: Aylanma | B4: Tarif
A5: 0-60 kun | B5: bepul | D5: 0 | E5: 0
A6: 61–180 kun | B6: kuniga har bir litri* uchun 12 so‘m | D6: 12 | E6: 61
A7: 181–360 kun | B7: kuniga har bir litr uchun 18 so‘m | D7: 18 | E7: 181
A8: 361 va undan ortiq kun* | B8: kuniga har bir litr uchun 24 so‘m | D8: 24 | E8: 361
A10: maksimal tarif | B10: Har bir tovar uchun kuniga 5000 so‘m | D10: 5000
A12: Maxsus tariflarga ega toifalar uchun tarif (1-ilova varag‘iga qarang)
A13: Aylanma | B13: Tarif
A14: 0–60 kun | B14: bepul | D14: 0 | E14: 0
A15: 61–180 kun | B15: kuniga har bir litr uchun 12 so‘m | D15: 12 | E15: 61
A16: 181–360 kun | B16: kuniga har bir litr uchun 14 so‘m | D16: 14 | E16: 181
A17: 361 va undan ortiq kun* | B17: kuniga har bir litr uchun 18 so‘m | D17: 18 | E17: 361
A19: maksimal tarif | B19: Har bir tovar uchun kuniga 3000 so‘m | D19: 3000
A21: Yangi stokni bepul saqlash
A22: 30 kundan 60 kungacha (2-ilova varag‘iga qarang)
A24: * hajm (litr) butun songacha yaxlitlanadi
A25: masalan:
A26: 1,6 litr -> 2 litr
A27: 5,2 litr -> 6 litr
A28: 104,3 litr -> 105 litr
A29: *** litrdagi hajm = uzunlik (mm) * eni (mm) * balandlik (mm) / 1000000
A30: ** shu jumladan aylanma hisoblash davrida sotuvlar bo‘lmagan bo‘lsa ham

Sheet Приложение 1
A1: Категории со сниженным тарифом
A3: Категория (уровень 1) | B3: Подкатегория (уровень 2) | C3: Тариф
A4: Аксессуары | B4: Горнолыжные аксессуары | C4: Специальный
A5: Аксессуары | B5: Женские аксессуары | C5: Специальный
A6: Аксессуары | B6: Религиозные аксессуары | C6: Специальный
A7: Аксессуары | B7: Аксессуары для путешествий | C7: Специальный
A8: Аксессуары | B8: Мужские аксессуары | C8: Специальный
A9: Одежда | B9: Одежда для мальчиков | C9: Специальный
A10: Аксессуары | B10: Аксессуары для мальчиков | C10: Специальный
A11: Одежда | B11: Одежда для новорождённых | C11: Специальный
A12: Обувь | B12: Обувь для мальчиков | C12: Специальный
A13: Аксессуары | B13: Аксессуары для девочек | C13: Специальный
A14: Обувь | B14: Обувь для девочек | C14: Специальный
... A25: Электроника | B25: Аксессуары для электроники | C25: Специальный

Sheet 1-ilova
A1: Pasaytirilgan tarif rejali toifalar
A3: Toifa (1-daraja) | B3: Quyi toifa (2-daraja) | C3: Tarif
A4: Aksessuarlar | B4: Tog' chang'i sport aksessuarlari | C4: Maxsus
A5: Aksessuarlar | B5: Ayollar aksessuarlari | C5: Maxsus
A6: Aksessuarlar | B6: Diniy aksessuarlar | C6: Maxsus
A7: Aksessuarlar | B7: Sayohat uchun aksessuarlar | C7: Maxsus
A8: Aksessuarlar | B8: Erkaklar aksessuarlari | C8: Maxsus
A9: Kiyim | B9: Oʻgʻil bolalar uchun kiyimlar | C9: Maxsus
A10: Aksessuarlar | B10: Oʻgʻil bolalar uchun aksessuarlar | C10: Maxsus
A11: Kiyim | B11: Yangi tugʻilgan chaqaloqlar uchun kiyimlar | C11: Maxsus
A12: Poyabzallar | B12: Oʻgʻil bolalar uchun poyabzal | C12: Maxsus
A13: Aksessuarlar | B13: Qizlar uchun aksessuarlar | C13: Maxsus
A14: Poyabzallar | B14: Qizlar uchun poyabzal | C14: Maxsus
... A25: Elektronika | B25: Elektronikalar uchun aksessuarlar | C25: Maxsus

Sheet Приложение 2
A1: Категории с увеличенным сроком бесплатного хранения нового стока
A3: Категория (уровень 1) | B3: Подкатегория (уровень 2) | C3: Срок бесплатного хранения для нового стока (дней)
A4: Автотовары | B4: Аксессуары и принадлежности | C4: 60
A5: Аксессуары | B5: Горнолыжные аксессуары | C5: 60
A6: Аксессуары | B6: Женские аксессуары | C6: 60
A7: Аксессуары | B7: Религиозные аксессуары | C7: 60
A8: Аксессуары | B8: Аксессуары для путешествий | C8: 60
A9: Аксессуары | B9: Мужские аксессуары | C9: 60
A10: Аксессуары | B10: Аксессуары для мальчиков | C10: 60
A11: Аксессуары | B11: Аксессуары для девочек | C11: 60
A12: Бытовая химия | B12: Чистящие и моющие средства | C12: 60
A13: Бытовая химия | B13: Средства для стирки | C13: 60
A14: Бытовая химия | B14: Бумажная продукция | C14: 60
A15: Детские товары | B15: Товары для кормления | C15: 60
... A83: Электроника | B83: Аксессуары для электроники | C83: 60
G833: Религиозные книги

Sheet 2-ilova
A1: Yangi stok uchun bepul saqlash muddati uzaytirilgan toifalar
A3: Toifa (1-daraja) | B3: Quyi toifa (2-daraja) | C3: Yangi stokda bepul saqlash muddati (kun)
A4: Aksessuarlar | B4: Tog' chang'i sport aksessuarlari | C4: 60
A5: Aksessuarlar | B5: Ayollar aksessuarlari | C5: 60
A6: Aksessuarlar | B6: Diniy aksessuarlar | C6: 60
A7: Aksessuarlar | B7: Sayohat uchun aksessuarlar | C7: 60
A8: Aksessuarlar | B8: Erkaklar aksessuarlari | C8: 60
A9: Kiyim | B9: Oʻgʻil bolalar uchun kiyimlar | C9: 60
A10: Aksessuarlar | B10: Oʻgʻil bolalar uchun aksessuarlar | C10: 60
A11: Kiyim | B11: Yangi tugʻilgan chaqaloqlar uchun kiyimlar | C11: 60
A12: Poyabzallar | B12: Oʻgʻil bolalar uchun poyabzal | C12: 60
A13: Aksessuarlar | B13: Qizlar uchun aksessuarlar | C13: 60
A14: Poyabzallar | B14: Qizlar uchun poyabzal | C14: 60
A15: Kiyim | B15: Qizlar uchun kiyimlar | C15: 60
... A83: Elektronika | B83: Elektronikalar uchun aksessuarlar | C83: 60
